Workbook

Sheet 1. Read me
A1: NLTF revenue model - glass-box walkthrough
A2: How the revenue forecasts on the dashboard are built, end to end, in plain language.
A4: What this workbook shows
B5: Our statistical models forecast three activity streams each quarter: petrol-vehicle travel per person (the AR(1) time-series model), light road-user-charge kilometres, and heavy road-user-charge kilometres.
B6: Those forecasts are turned into revenue with assumptions taken directly from the Ministry of Transport: the MBU26 class mix (how light travel divides into petrol, conventional RUC, battery-electric and plug-in hybrid), fuel intensity (litres per 100 km), and the effective duty and RUC rates.
B7: The electric-vehicle transition itself comes from MoT's Vehicle Fleet Model (VFM 202405): sheet 2 shows the official share curves, and sheet 3 shows the evidence that the S-shape is a property of the data - a no-fitting growth-rate signature, a nine-way form tournament judged on an unseen decade, a fleet-turnover reconstruction with no curve at all, and the observed NZ outturns - before presenting the dashboard's dials as measurements of that shape.
B8: Sheets 4-7 then walk line by line from the model forecasts to total NLTF revenue. Sheet 8 proves the result: every line reconciles to the committed dashboard data to well under $0.01m.
B9: No opaque weights are used anywhere: every step is an ordinary spreadsheet formula you can audit.
A11: How to read the colours
B12: Blue - an input taken from a named source (the source cell/row is written beside it)
B13: Black - a formula computed on the same sheet
B14: Green - a value linked from another sheet in this workbook
A16: The pipeline at a glance
B17: Model forecasts (sheet 4) -> light-fleet split using MoT class mix (sheet 5) -> litres, rates and revenue per stream (sheet 6) -> NLTF rollup (sheet 7) -> reconciliation to the dashboard (sheet 8)
A19: Provenance (hash-verified sources)
B20: MoT Vehicle Fleet Model outputs | C20: data/source_workbooks/VFM202405_outputs_summary_V3.xlsx | 2c49dc3e2fd6b4f083c0d8e8f52b36f34216bc37eac78ed4329347692ac4b4ab
B21: VFM documentation | C21: data/source_workbooks/Vehicle-Fleet-Model-Documentation_202405_v7.pdf | 4cf223d522545131b9cba0d8a765ff0d3a56f751bb7192e97306d61e942fdd4c
B22: MBU26 official spine | C22: data/revenue_model_source_pack/mbu26_annual_spine/mbu26_official_annual.csv | row/cell references quoted per line in sheets 5-7
B23: Committed dashboard pack (AR(1) engine) | C23: data/engine_ar1/current_revenue_outlook/ | reconciled line by line on sheet 8
A25: Scope notes
B26: Scenario: Base case, June years FY2026-FY2050 (the dashboard's default view). FY2025 is anchored to published MBU26 actuals and is not recomputed.
B27: All revenue is $m nominal, excluding GST - the same basis as MBU26. June year FY(t) runs July(t-1) to June(t).
B28: Admin fees, refunds, LPG/CNG, motor-vehicle registration components and the track-user charge are taken directly from MBU26 (they are not modelled); each is labelled with its MBU26 source cell.
B29: The e-RUC transition and the advanced dashboard levers are display-time what-ifs and sit outside this committed baseline.

Sheet 2. MoT VFM curves
A1: MoT Vehicle Fleet Model 202405 - official share curves
A2: Read straight from the MoT workbook, sheet 'Raw data (wem202405)' (WEM = with existing measures). Light pool = diesel + diesel-hybrid (conventional) + battery-electric + petrol plug-in VKT for light passenger + light commercial vehicles. June year = average of the two calendar years.
A4: Share of the light RUC pool by power type, plus heavy electric share and petrol share of all light travel
B5: Base EV scenario | G5: Fast EV scenario | L5: Slow EV scenario
A6: June year | B6: Conventional light (share) | C6: Battery-electric light (share) | D6: Plug-in hybrid (share) | E6: Heavy electric (share) | F6: Petrol share of light VKT | G6: Conventional light (share) | H6: Battery-electric light (share) | I6: Plug-in hybrid (share) | J6: Heavy electric (share) | K6: Petrol share of light VKT | L6: Conventional light (share) | M6: Battery-electric light (share) | N6: Plug-in hybrid (share) | O6: Heavy electric (share) | P6: Petrol share of light VKT
A7: 2025 | B7: 0.892358 | C7: 0.072132 | D7: 0.03551 | E7: 0.001932 | F7: 0.682852 | G7: 0.886565 | H7: 0.074746 | I7: 0.038689 | J7: 0.001992 | K7: 0.681079 | L7: 0.901566 | M7: 0.064852 | N7: 0.033583 | O7: 0.001803 | P7: 0.685554
A8: 2026 | B8: 0.871553 | C8: 0.0843 | D8: 0.044146 | E8: 0.002179 | F8: 0.6772 | G8: 0.860699 | H8: 0.088718 | I8: 0.050583 | J8: 0.002317 | K8: 0.674189 | L8: 0.887705 | M8: 0.072452 | N8: 0.039843 | O8: 0.001905 | P8: 0.68194
A9: 2027 | B9: 0.843887 | C9: 0.100828 | D9: 0.055284 | E9: 0.002525 | F9: 0.669529 | G9: 0.825712 | H9: 0.108262 | I9: 0.066026 | J9: 0.002807 | K9: 0.664652 | L9: 0.869223 | M9: 0.082746 | N9: 0.048031 | O9: 0.002051 | P9: 0.677005
A10: 2028 | B10: 0.809462 | C10: 0.122362 | D10: 0.068176 | E10: 0.003192 | F10: 0.659778 | G10: 0.783022 | H10: 0.134209 | I10: 0.082769 | J10: 0.003798 | K10: 0.652474 | L10: 0.844429 | M10: 0.097848 | N10: 0.057723 | O10: 0.002414 | P10: 0.670367
A11: 2029 | B11: 0.771248 | C11: 0.14713 | D11: 0.081621 | E11: 0.00433 | F11: 0.648739 | G11: 0.736682 | H11: 0.164417 | I11: 0.098901 | J11: 0.00556 | K11: 0.638693 | L11: 0.814749 | M11: 0.116915 | N11: 0.068336 | O11: 0.003095 | P11: 0.662481
A12: 2030 | B12: 0.732447 | C12: 0.172989 | D12: 0.094564 | E12: 0.005965 | F12: 0.637156 | G12: 0.690103 | H12: 0.196166 | I12: 0.113731 | J12: 0.008216 | K12: 0.624099 | L12: 0.783782 | M12: 0.13728 | N12: 0.078938 | O12: 0.004054 | P12: 0.654162
A13: 2031 | B13: 0.694056 | C13: 0.199459 | D13: 0.106485 | E13: 0.008248 | F13: 0.62527 | G13: 0.644526 | H13: 0.228373 | I13: 0.127101 | J13: 0.01211 | K13: 0.608828 | L13: 0.753142 | M13: 0.157968 | N13: 0.08889 | O13: 0.005305 | P13: 0.645784
A14: 2032 | B14: 0.655046 | C14: 0.227075 | D14: 0.117879 | E14: 0.011465 | F14: 0.612422 | G14: 0.599059 | H14: 0.261642 | I14: 0.1393 | J14: 0.017855 | K14: 0.592261 | L14: 0.722167 | M14: 0.179424 | N14: 0.098409 | O14: 0.006932 | P14: 0.636907
A15: 2033 | B15: 0.614952 | C15: 0.256837 | D15: 0.12821 | E15: 0.015686 | F15: 0.597969 | G15: 0.553243 | H15: 0.297176 | I15: 0.149581 | J15: 0.025776 | K15: 0.573856 | L15: 0.690293 | M15: 0.202578 | N15: 0.107129 | O15: 0.008909 | P15: 0.626973
A16: 2034 | B16: 0.573192 | C16: 0.290136 | D16: 0.136672 | E16: 0.020694 | F16: 0.581547 | G16: 0.506409 | H16: 0.336032 | I16: 0.157559 | J16: 0.035671 | K16: 0.553045 | L16: 0.656578 | M16: 0.228937 | N16: 0.114485 | O16: 0.011106 | P16: 0.615689
A17: 2035 | B17: 0.530272 | C17: 0.327151 | D17: 0.142577 | E17: 0.026349 | F17: 0.562776 | G17: 0.459004 | H17: 0.378044 | I17: 0.162952 | J17: 0.047285 | K17: 0.529479 | L17: 0.621051 | M17: 0.258895 | N17: 0.120054 | O17: 0.013453 | P17: 0.602654
A18: 2036 | B18: 0.48761 | C18: 0.36751 | D18: 0.14488 | E18: 0.032767 | F18: 0.54169 | G18: 0.4129 | H18: 0.422558 | I18: 0.164542 | J18: 0.060637 | K18: 0.503517 | L18: 0.584361 | M18: 0.292092 | N18: 0.123547 | O18: 0.01604 | P18: 0.587642
... A32: 2050 | B32: 0.119794 | C32: 0.821498 | D32: 0.058708 | E32: 0.198635 | F32: 0.163893 | G32: 0.082622 | H32: 0.857992 | I32: 0.059386 | J32: 0.343394 | K32: 0.1241 | L32: 0.172955 | M32: 0.76919 | N32: 0.057856 | O32: 0.095209 | P32: 0.231935
A34: Source rows: VKT by scenario x vehicle type (LPV, LCV, M Truck, H Truck) x power type (Petrol, Hybrid petrol, Diesel, Hybrid diesel, Electric, Petrol plug-in) x calendar year, from the raw-output sheet of VFM202405_outputs_summary_V3.xlsx.

Sheet 3. Why an S-curve
A1: Why an S-curve? Because the data says so - four tests our formula could fail
A2: A fitted curve proves nothing by itself: with enough parameters a formula can mimic anything. So this sheet starts from falsifiable tests of the shape, not from our formula.
A4: The four tests
A5: 1. Growth-rate signature - saturating adoption has a straight-line fingerprint that needs NO curve fitting; the line's endpoints ARE the ceiling and speed, measured from MoT's own series.
A6: 2. Form tournament - fit nine candidate shapes on 2001-2040, judge them on the unseen 2041-2050 decade. Flexible forms mimic in-sample and fail out-of-sample; only a form whose shape matches the data survives.
A7: 3. Mechanism - rebuild the fleet share from MoT's own registration flows and fleet turnover with no functional form at all: the S-curve emerges from the arithmetic.
A8: 4. Observed outturns - New Zealand's actual fleet shares (outside the VFM) sit on the projected toe.
A10: Test 1 - the growth-rate signature (no curve fitting anywhere)
A11: If adoption saturates, the relative growth rate s'/s falls in a straight line as the share s rises: s'/s = speed x (1 - s / ceiling). Straight-line behaviour is falsifiable - and the intercept and x-intercept of that line ARE the speed and ceiling, read from MoT's series rather than chosen by us.
A12: June year | B12: BEV share (sheet 2, base) | C12: Mid-point share | D12: Relative growth = change / mid share
A13: 2025 | B13: ='2. MoT VFM curves'!C7
A14: 2026 | B14: ='2. MoT VFM curves'!C8 | C14: =(B14+B13)/2 | D14: =(B14-B13)/C14 | F14: Straight-line fit R-squared | H14: =RSQ(D14:D38,C14:C38)
A15: 2027 | B15: ='2. MoT VFM curves'!C9 | C15: =(B15+B14)/2 | D15: =(B15-B14)/C15 | F15: Speed constant (line intercept) | H15: =INTERCEPT(D14:D38,C14:C38)
A16: 2028 | B16: ='2. MoT VFM curves'!C10 | C16: =(B16+B15)/2 | D16: =(B16-B15)/C16 | F16: Ceiling (line's x-intercept) | H16: =-INTERCEPT(D14:D38,C14:C38)/SLOPE(D14:D38,C14:C38)
A17: 2029 | B17: ='2. MoT VFM curves'!C11 | C17: =(B17+B16)/2 | D17: =(B17-B16)/C17 | F17: Dashboard dial: speed | H17: =B130
A18: 2030 | B18: ='2. MoT VFM curves'!C12 | C18: =(B18+B17)/2 | D18: =(B18-B17)/C18 | F18: Dashboard dial: ceiling | H18: =B129
A19: 2031 | B19: ='2. MoT VFM curves'!C13 | C19: =(B19+B18)/2 | D19: =(B19-B18)/C19
A20: 2032 | B20: ='2. MoT VFM curves'!C14 | C20: =(B20+B19)/2 | D20: =(B20-B19)/C20 | F20: The measured speed and ceiling match the dashboard's dials - the dials are measurements of MoT's series, not free coefficients.
A21: 2033 | B21: ='2. MoT VFM curves'!C15 | C21: =(B21+B20)/2 | D21: =(B21-B20)/C21
A22: 2034 | B22: ='2. MoT VFM curves'!C16 | C22: =(B22+B21)/2 | D22: =(B22-B21)/C22
A23: 2035 | B23: ='2. MoT VFM curves'!C17 | C23: =(B23+B22)/2 | D23: =(B23-B22)/C23
A24: 2036 | B24: ='2. MoT VFM curves'!C18 | C24: =(B24+B23)/2 | D24: =(B24-B23)/C24
A25: 2037 | B25: ='2. MoT VFM curves'!C19 | C25: =(B25+B24)/2 | D25: =(B25-B24)/C25
A26: 2038 | B26: ='2. MoT VFM curves'!C20 | C26: =(B26+B25)/2 | D26: =(B26-B25)/C26
A27: 2039 | B27: ='2. MoT VFM curves'!C21 | C27: =(B27+B26)/2 | D27: =(B27-B26)/C27
A28: 2040 | B28: ='2. MoT VFM curves'!C22 | C28: =(B28+B27)/2 | D28: =(B28-B27)/C28
A29: 2041 | B29: ='2. MoT VFM curves'!C23 | C29: =(B29+B28)/2 | D29: =(B29-B28)/C29
A30: 2042 | B30: ='2. MoT VFM curves'!C24 | C30: =(B30+B29)/2 | D30: =(B30-B29)/C30
A31: 2043 | B31: ='2. MoT VFM curves'!C25 | C31: =(B31+B30)/2 | D31: =(B31-B30)/C31
A32: 2044 | B32: ='2. MoT VFM curves'!C26 | C32: =(B32+B31)/2 | D32: =(B32-B31)/C32
... A38: 2050 | B38: ='2. MoT VFM curves'!C32 | C38: =(B38+B37)/2 | D38: =(B38-B37)/C38
A40: Test 2 - the form tournament (fit 2001-2040, judged on the unseen 2041-2050)
A41: Functional form | B41: Parameters | C41: Fit error 2001-2040 (pp) | D41: Error on unseen 2041-2050 (pp) | E41: Predicted 2050 share (%)
A42: logistic (S-curve) | B42: 3 | C42: 0.72364485 | D42: 2.5743192 | E42: 79.299269
A43: power | B43: 2 | C43: 2.0204981 | D43: 4.9687328 | E43: 93.356835
A44: quadratic | B44: 3 | C44: 2.1554219 | D44: 8.1224501 | E44: 99.986758
A45: Richards (S-curve) | B45: 4 | C45: 0.37174563 | D45: 11.700548 | E45: 104.32407
A46: Gompertz (S-curve) | B46: 3 | C46: 0.35038036 | D46: 12.686669 | E46: 106.17193
A47: Bass diffusion (S-curve) | B47: 3 | C47: 3.7833294 | D47: 20.372449 | E47: 55.117075
A48: cubic | B48: 4 | C48: 0.33810599 | D48: 26.967255 | E48: 132.87204
A49: linear | B49: 2 | C49: 8.5931676 | D49: 31.172929 | E49: 48.498795
A50: exponential | B50: 2 | C50: 1.9207927 | D50: 75.183399 | E50: 226.7154
A52: VFM's actual 2050 base-scenario share: 82.1%. The forms that fit BEST in-sample (cubic, Gompertz, Richards, 0.3-0.4pp) miss the unseen decade by 12-27 points - that is exactly what 'a formula can mimic anything' looks like. The logistic is the only form that both fits and extrapolates: the shape, not parameter flexibility, is doing the work.
A54: Computed by scripts/uptake_shape_lab.py from the VFM workbook's raw outputs; full results (all three scenarios) in artifacts/uptake_shape_lab/.
A56: Test 3 - the mechanism: fleet-turnover arithmetic (no curve at all)
A57: VFM is a fleet-turnover model. Take the 2023 fleet share as the only starting value, then apply next year = this year + turnover x (new-entry share - this year), using MoT's own registration mix and turnover. No functional form appears anywhere - and the S-curve emerges from the arithmetic.
A58: Calendar year | B58: BEV share of new light entries | C58: Fleet turnover (entries/stock) | D58: VFM fleet BEV share | E58: Reconstructed share (formula) | F58: Gap (pp)
A59: 2023 | B59: 0.34331063 | C59: 0.075551642 | D59: 0.071866475 | E59: =D59 | F59: =(E59-D59)*100
A60: 2024 | B60: 0.20495296 | C60: 0.060002576 | D60: 0.080931727 | E60: =E59+C59*(B59-E59) | F60: =(E60-D60)*100
A61: 2025 | B61: 0.23761941 | C61: 0.064022095 | D61: 0.092064359 | E61: =E60+C60*(B60-E60) | F61: =(E61-D61)*100
A62: 2026 | B62: 0.30646485 | C62: 0.068431807 | D62: 0.10789878 | E62: =E61+C61*(B61-E61) | F62: =(E62-D62)*100
A63: 2027 | B63: 0.3649065 | C63: 0.073970536 | D63: 0.12830409 | E63: =E62+C62*(B62-E62) | F63: =(E63-D63)*100
A64: 2028 | B64: 0.40314637 | C64: 0.077015789 | D64: 0.15117952 | E64: =E63+C63*(B63-E63) | F64: =(E64-D64)*100
A65: 2029 | B65: 0.42167026 | C65: 0.077623215 | D65: 0.17419276 | E65: =E64+C64*(B64-E64) | F65: =(E65-D65)*100
A66: 2030 | B66: 0.44329285 | C66: 0.076974012 | D66: 0.1972904 | E66: =E65+C65*(B65-E65) | F66: =(E66-D66)*100
A67: 2031 | B67: 0.4681835 | C67: 0.077781167 | D67: 0.22114012 | E67: =E66+C66*(B66-E66) | F67: =(E67-D67)*100
A68: 2032 | B68: 0.49729868 | C68: 0.080952536 | D68: 0.24665054 | E68: =E67+C67*(B67-E67) | F68: =(E68-D68)*100
A69: 2033 | B69: 0.5492982 | C69: 0.082906263 | D69: 0.27528293 | E69: =E68+C68*(B68-E68) | F69: =(E69-D69)*100
A70: 2034 | B70: 0.59981782 | C70: 0.085996443 | D70: 0.30705238 | E70: =E69+C69*(B69-E69) | F70: =(E70-D70)*100
A71: 2035 | B71: 0.66174276 | C71: 0.087755177 | D71: 0.34233732 | E71: =E70+C70*(B70-E70) | F71: =(E71-D71)*100
... A86: 2050 | B86: 0.94468439 | C86: 0.068370171 | D86: 0.79889286 | E86: =E85+C85*(B85-E85) | F86: =(E86-D86)*100
A88: The reconstruction tracks VFM's fleet share within ~7 points over three decades and sits consistently BELOW it - exactly as it should, because real scrappage retires older conventional vehicles first while this simple version retires the average mix. A rising sales mix filtered through roughly 8% a year of fleet turnover IS the S-curve. Source: 'Registrations' and raw-output sheets of the VFM workbook.
A90: Test 4 - observed New Zealand outturns (outside the VFM)
A91: June year | B91: Observed light BEV share (MBU26 actuals) | C91: VFM base scenario | D91: Gap (pp)
A92: 2024 | B92: 0.037716011 | C92: 0.059430724 | D92: =(B92-C92)*100
A93: 2025 | B93: 0.060654622 | C93: 0.072131936 | D93: =(B93-C93)*100
A95: MBU26 splits the light BEV class out only from FY2024, so two observed points exist so far; both sit on the toe of the projected curve with the gap closing. This test grows teeth every year as outturns land. The straight-line growth signature above is also the classic technology-substitution result (Fisher & Pry, 1971), observed across dozens of adoptions from colour TV to smartphones - and famously completed by Norway's electric fleet.
A112: The dashboard's dials - a readable parameterisation of the measured shape
A113: Lever (plain language) | B113: MoT VFM base | C113: MoT VFM fast | D113: MoT VFM slow
A114: Battery-electric: fastest uptake speed (share points per year) | B114: 0.0425 | C114: 0.0475 | D114: 0.0425
A115: Battery-electric: year of fastest uptake | B115: 2038 | C115: 2036.5 | D115: 2039.5
A116: Battery-electric: share of light RUC pool reached by 2050 | B116: 0.83 | C116: 0.86 | D116: 0.78
A117: Plug-in hybrid: share at FY2025 | B117: 0.036 | C117: 0.039 | D117: 0.034
A118: Plug-in hybrid: rise per year while growing (share points) | B118: 0.011 | C118: 0.013 | D118: 0.009
A119: Plug-in hybrid: peak share | B119: 0.155 | C119: 0.175 | D119: 0.135
A120: Plug-in hybrid: decline rate after the peak (per year) | B120: 0.06 | C120: 0.065 | D120: 0.055
A121: Petrol displacement: fastest speed (share points per year) | B121: 0.0425 | C121: 0.0425 | D121: 0.0425
A122: Petrol displacement: year of fastest displacement | B122: 2042 | C122: 2040.5 | D122: 2043.5
A123: Petrol displacement: share of FY2025 petrol travel displaced by 2050 | B123: 0.78 | C123: 0.84 | D123: 0.68
A124: Heavy electric: fastest uptake speed (share points per year) | B124: 0.0175 | C124: 0.025 | D124: 0.01
A125: Heavy electric: midpoint year | B125: 2051 | C125: 2046 | D125: 2054
A126: Heavy electric: share of heavy pool by 2050 | B126: 0.21 | C126: 0.36 | D126: 0.1
A128: Derived curve constants (base preset) - solved so each S-curve passes through its 2050 share at the stated speed
A129: BEV curve ceiling (saturation share) | B129: 0.92048716 | C129: Solved numerically (bisection) so the S-curve hits the 2050 share at the stated peak speed
A130: BEV curve steepness | B130: =4*B114/B129 | C130: Equals 4 x peak speed / ceiling
A131: Petrol displacement ceiling | B131: 0.97269715 | C131: Solved the same way for the petrol displacement curve
A132: Petrol displacement steepness | B132: =4*B121/B131 | C132: Equals 4 x peak speed / ceiling
A133: Heavy electric ceiling | B133: 0.45493111 | C133: Solved the same way for the heavy curve
A134: Heavy electric steepness | B134: =4*B124/B133 | C134: Equals 4 x peak speed / ceiling
A135: Plug-in hybrid peak year | B135: =2025+(B119-B117)/B118 | C135: Start share rises linearly until it reaches the peak share
A137: Base-preset curves vs MoT official base scenario (green = linked from sheet 2)
A138: June year | B138: BEV share (our formula) | C138: BEV share (MoT VFM) | D138: BEV gap (pp) | E138: PHEV share (our formula) | F138: PHEV share (MoT VFM) | G138: PHEV gap (pp) | H138: Petrol retained vs FY2025 (our formula) | I138: Heavy electric share (our formula) | J138: Heavy electric share (MoT VFM) | K138: Heavy gap (pp)
A139: 2025 | B139: =B129/(1+EXP(-B130*(A139-B115))) | C139: ='2. MoT VFM curves'!C7 | D139: =(B139-C139)*100 | E139: =IF(A139<=B135,MIN(B117+B118*(A139-2025),B119),B119*EXP(-B120*(A139-B135))) | F139: ='2. MoT VFM curves'!D7 | G139: =(E139-F139)*100 | H139: =(1-B131/(1+EXP(-B132*(A139-B122))))/(1-B131/(1+EXP(-B132*(2025-B122)))) | I139: =B133/(1+EXP(-B134*(A139-B125)))-B133/(1+EXP(-B134*(2025-B125))) | J139: ='2. MoT VFM curves'!E7 | K139: =(I139-J139)*100
A140: 2026 | B140: =B129/(1+EXP(-B130*(A140-B115))) | C140: ='2. MoT VFM curves'!C8 | D140: =(B140-C140)*100 | E140: =IF(A140<=B135,MIN(B117+B118*(A140-2025),B119),B119*EXP(-B120*(A140-B135))) | F140: ='2. MoT VFM curves'!D8 | G140: =(E140-F140)*100 | H140: =(1-B131/(1+EXP(-B132*(A140-B122))))/(1-B131/(1+EXP(-B132*(2025-B122)))) | I140: =B133/(1+EXP(-B134*(A140-B125)))-B133/(1+EXP(-B134*(2025-B125))) | J140: ='2. MoT VFM curves'!E8 | K140: =(I140-J140)*100
A141: 2027 | B141: =B129/(1+EXP(-B130*(A141-B115))) | C141: ='2. MoT VFM curves'!C9 | D141: =(B141-C141)*100 | E141: =IF(A141<=B135,MIN(B117+B118*(A141-2025),B119),B119*EXP(-B120*(A141-B135))) | F141: ='2. MoT VFM curves'!D9 | G141: =(E141-F141)*100 | H141: =(1-B131/(1+EXP(-B132*(A141-B122))))/(1-B131/(1+EXP(-B132*(2025-B122)))) | I141: =B133/(1+EXP(-B134*(A141-B125)))-B133/(1+EXP(-B134*(2025-B125))) | J141: ='2. MoT VFM curves'!E9 | K141: =(I141-J141)*100
A142: 2028 | B142: =B129/(1+EXP(-B130*(A142-B115))) | C142: ='2. MoT VFM curves'!C10 | D142: =(B142-C142)*100 | E142: =IF(A142<=B135,MIN(B117+B118*(A142-2025),B119),B119*EXP(-B120*(A142-B135))) | F142: ='2. MoT VFM curves'!D10 | G142: =(E142-F142)*100 | H142: =(1-B131/(1+EXP(-B132*(A142-B122))))/(1-B131/(1+EXP(-B132*(2025-B122)))) | I142: =B133/(1+EXP(-B134*(A142-B125)))-B133/(1+EXP(-B134*(2025-B125))) | J142: ='2. MoT VFM curves'!E10 | K142: =(I142-J142)*100
A143: 2029 | B143: =B129/(1+EXP(-B130*(A143-B115))) | C143: ='2. MoT VFM curves'!C11 | D143: =(B143-C143)*100 | E143: =IF(A143<=B135,MIN(B117+B118*(A143-2025),B119),B119*EXP(-B120*(A143-B135))) | F143: ='2. MoT VFM curves'!D11 | G143: =(E143-F143)*100 | H143: =(1-B131/(1+EXP(-B132*(A143-B122))))/(1-B131/(1+EXP(-B132*(2025-B122)))) | I143: =B133/(1+EXP(-B134*(A143-B125)))-B133/(1+EXP(-B134*(2025-B125))) | J143: ='2. MoT VFM curves'!E11 | K143: =(I143-J143)*100
A144: 2030 | B144: =B129/(1+EXP(-B130*(A144-B115))) | C144: ='2. MoT VFM curves'!C12 | D144: =(B144-C144)*100 | E144: =IF(A144<=B135,MIN(B117+B118*(A144-2025),B119),B119*EXP(-B120*(A144-B135))) | F144: ='2. MoT VFM curves'!D12 | G144: =(E144-F144)*100 | H144: =(1-B131/(1+EXP(-B132*(A144-B122))))/(1-B131/(1+EXP(-B132*(2025-B122)))) | I144: =B133/(1+EXP(-B134*(A144-B125)))-B133/(1+EXP(-B134*(2025-B125))) | J144: ='2. MoT VFM curves'!E12 | K144: =(I144-J144)*100
A145: 2031 | B145: =B129/(1+EXP(-B130*(A145-B115))) | C145: ='2. MoT VFM curves'!C13 | D145: =(B145-C145)*100 | E145: =IF(A145<=B135,MIN(B117+B118*(A145-2025),B119),B119*EXP(-B120*(A145-B135))) | F145: ='2. MoT VFM curves'!D13 | G145: =(E145-F145)*100 | H145: =(1-B131/(1+EXP(-B132*(A145-B122))))/(1-B131/(1+EXP(-B132*(2025-B122)))) | I145: =B133/(1+EXP(-B134*(A145-B125)))-B133/(1+EXP(-B134*(2025-B125))) | J145: ='2. MoT VFM curves'!E13 | K145: =(I145-J145)*100
A146: 2032 | B146: =B129/(1+EXP(-B130*(A146-B115))) | C146: ='2. MoT VFM curves'!C14 | D146: =(B146-C146)*100 | E146: =IF(A146<=B135,MIN(B117+B118*(A146-2025),B119),B119*EXP(-B120*(A146-B135))) | F146: ='2. MoT VFM curves'!D14 | G146: =(E146-F146)*100 | H146: =(1-B131/(1+EXP(-B132*(A146-B122))))/(1-B131/(1+EXP(-B132*(2025-B122)))) | I146: =B133/(1+EXP(-B134*(A146-B125)))-B133/(1+EXP(-B134*(2025-B125))) | J146: ='2. MoT VFM curves'!E14 | K146: =(I146-J146)*100
...

Sheet 4. Engine forecasts
A1: What the models forecast (quarterly)
A2: The engine's three activity forecasts, quarter by quarter. Petrol travel per person comes from the AR(1) time-series model; light and heavy RUC kilometres from their governed models. Population is the scenario input used to gross per-person travel up to national kilometres.
A4: Quarterly model outputs and population, FY2026-FY2050 (blue = committed model/pack values)
A5: June year | B5: Quarter | C5: Value source | D5: Petrol travel per person (km/quarter) | E5: Population (people) | F5: Population source | G5: Petrol pool (million km) = travel x people / 1m | H5: Light RUC km (model, km) | I5: Light RUC (million km) | J5: Heavy RUC km (model, km) | K5: Heavy RUC (million km)
A6: 2026 | B6: 2025Q3 | C6: Actual (published outturn) | D6: 1544.6797 | E6: 5363105.7 | F6: MBU26 proxy: petrol VKT / VKT per capita (FY2026) | G6: =D6*E6/1000000 | H6: 3122958703 | I6: =H6/1000000 | J6: 978994143 | K6: =J6/1000000
A7: 2026 | B7: 2025Q4 | C7: Actual (published outturn) | D7: 1565.5435 | E7: 5363105.7 | F7: MBU26 proxy: petrol VKT / VKT per capita (FY2026) | G7: =D7*E7/1000000 | H7: 3307965543 | I7: =H7/1000000 | J7: 1064388483 | K7: =J7/1000000
A8: 2026 | B8: 2026Q1 | C8: Model forecast (AR(1) engine) | D8: 1529.2601 | E8: 5353979.1 | F8: Scenario input workbook | G8: =D8*E8/1000000 | H8: 3.3569016e+09 | I8: =H8/1000000 | J8: 1.0201181e+09 | K8: =J8/1000000
A9: 2026 | B9: 2026Q2 | C9: Model forecast (AR(1) engine) | D9: 1504.8384 | E9: 5365985.2 | F9: Scenario input workbook | G9: =D9*E9/1000000 | H9: 3.1704986e+09 | I9: =H9/1000000 | J9: 9.8161214e+08 | K9: =J9/1000000
A10: 2027 | B10: 2026Q3 | C10: Model forecast (AR(1) engine) | D10: 1499.4324 | E10: 5378018.1 | F10: Scenario input workbook | G10: =D10*E10/1000000 | H10: 3.0449757e+09 | I10: =H10/1000000 | J10: 9.9711905e+08 | K10: =J10/1000000
A11: 2027 | B11: 2026Q4 | C11: Model forecast (AR(1) engine) | D11: 1509.7476 | E11: 5390078 | F11: Scenario input workbook | G11: =D11*E11/1000000 | H11: 3.0632614e+09 | I11: =H11/1000000 | J11: 1.0664951e+09 | K11: =J11/1000000
A12: 2027 | B12: 2027Q1 | C12: Model forecast (AR(1) engine) | D12: 1484.7799 | E12: 5400826 | F12: Scenario input workbook | G12: =D12*E12/1000000 | H12: 3.2627985e+09 | I12: =H12/1000000 | J12: 1.0345993e+09 | K12: =J12/1000000
A13: 2027 | B13: 2027Q2 | C13: Model forecast (AR(1) engine) | D13: 1472.8188 | E13: 5411595.4 | F13: Scenario input workbook | G13: =D13*E13/1000000 | H13: 3.2908957e+09 | I13: =H13/1000000 | J13: 1.0020567e+09 | K13: =J13/1000000
A14: 2028 | B14: 2027Q3 | C14: Model forecast (AR(1) engine) | D14: 1477.2845 | E14: 5422386.2 | F14: Scenario input workbook | G14: =D14*E14/1000000 | H14: 3.1617573e+09 | I14: =H14/1000000 | J14: 1.0144757e+09 | K14: =J14/1000000
A15: 2028 | B15: 2027Q4 | C15: Model forecast (AR(1) engine) | D15: 1494.6307 | E15: 5433198.6 | F15: Scenario input workbook | G15: =D15*E15/1000000 | H15: 3.3810837e+09 | I15: =H15/1000000 | J15: 1.070992e+09 | K15: =J15/1000000
A16: 2028 | B16: 2028Q1 | C16: Model forecast (AR(1) engine) | D16: 1474.4051 | E16: 5444032.6 | F16: Scenario input workbook | G16: =D16*E16/1000000 | H16: 3.3859085e+09 | I16: =H16/1000000 | J16: 1.0379169e+09 | K16: =J16/1000000
A17: 2028 | B17: 2028Q2 | C17: Model forecast (AR(1) engine) | D17: 1465.1851 | E17: 5454888.1 | F17: Scenario input workbook | G17: =D17*E17/1000000 | H17: 3.4117814e+09 | I17: =H17/1000000 | J17: 1.0107336e+09 | K17: =J17/1000000
... A105: 2050 | B105: 2050Q2 | C105: Model forecast (AR(1) engine) | D105: 1276.5212 | E105: 6254674.1 | F105: Scenario input workbook | G105: =D105*E105/1000000 | H105: 5.6523057e+09 | I105: =H105/1000000 | J105: 1.1612761e+09 | K105: =J105/1000000

Sheet 5. Light fleet split
A1: Splitting the light fleet: petrol, conventional RUC, battery-electric, plug-in hybrid
A2: We pool the model's petrol travel and light RUC kilometres into one light-mobility universe, then split it using MoT's official MBU26 class mix. One allocation assumption decides how much of the electric switch comes out of each pool - no other weights are involved.
A4: Per June year. Green = linked from sheet 4; blue = MBU26 official inputs (source cell quoted at right)
A5: June year | B5: Petrol pool P (million km) | C5: Light RUC pool L (million km) | D5: Light universe U = P + L | E5: MoT petrol VKT (million km) | F5: MoT conventional RUC km | G5: MoT battery-electric km | H5: MoT plug-in hybrid km | I5: MoT light total (sum) | J5: MoT petrol share | K5: MoT conventional share | L5: MoT BEV share | M5: MoT PHEV share | N5: Electric switch (million km) = U x (BEV+PHEV shares) | O5: EV switch drawn from RUC pool (share) | P5: Battery-electric km = U x BEV share | Q5: Plug-in hybrid km = U x PHEV share | R5: Petrol km kept = P - (1 - split) x switch | S5: Conventional RUC km = L - split x switch | T5: Check: four classes sum back to U | U5: Largest gap to MoT mix (pp) | V5: MBU26 source cells (this June year)
A6: 2026 | B6: =SUM('4. Engine forecasts'!G6:G9) | C6: =SUM('4. Engine forecasts'!I6:I9) | D6: =B6+C6 | E6: 31834.731 | F6: 12899.125 | G6: 1209.3791 | H6: 633.39411 | I6: =SUM(E6:H6) | J6: =E6/I6 | K6: =F6/I6 | L6: =G6/I6 | M6: =H6/I6 | N6: =D6*(L6+M6) | O6: 0.33247386 | P6: =D6*L6 | Q6: =D6*M6 | R6: =B6-(1-O6)*N6 | S6: =C6-O6*N6 | T6: =P6+Q6+R6+S6-D6 | U6: =MAX(ABS(R6/D6-J6),ABS(S6/D6-K6),ABS(P6/D6-L6),ABS(Q6/D6-M6))*100 | V6: MBU26 sheet: AB16 petrol VKT | AB10 conventional | AB12 BEV | AB14 PHEV
A7: 2027 | B7: =SUM('4. Engine forecasts'!G10:G13) | C7: =SUM('4. Engine forecasts'!I10:I13) | D7: =B7+C7 | E7: 32115.243 | F7: 12939.637 | G7: 1572.1948 | H7: 866.45344 | I7: =SUM(E7:H7) | J7: =E7/I7 | K7: =F7/I7 | L7: =G7/I7 | M7: =H7/I7 | N7: =D7*(L7+M7) | O7: 0.34270454 | P7: =D7*L7 | Q7: =D7*M7 | R7: =B7-(1-O7)*N7 | S7: =C7-O7*N7 | T7: =P7+Q7+R7+S7-D7 | U7: =MAX(ABS(R7/D7-J7),ABS(S7/D7-K7),ABS(P7/D7-L7),ABS(Q7/D7-M7))*100 | V7: MBU26 sheet: AC16 petrol VKT | AC10 conventional | AC12 BEV | AC14 PHEV
A8: 2028 | B8: =SUM('4. Engine forecasts'!G14:G17) | C8: =SUM('4. Engine forecasts'!I14:I17) | D8: =B8+C8 | E8: 32346.453 | F8: 13427.717 | G8: 1989.376 | H8: 1114.14 | I8: =SUM(E8:H8) | J8: =E8/I8 | K8: =F8/I8 | L8: =G8/I8 | M8: =H8/I8 | N8: =D8*(L8+M8) | O8: 0.35290586 | P8: =D8*L8 | Q8: =D8*M8 | R8: =B8-(1-O8)*N8 | S8: =C8-O8*N8 | T8: =P8+Q8+R8+S8-D8 | U8: =MAX(ABS(R8/D8-J8),ABS(S8/D8-K8),ABS(P8/D8-L8),ABS(Q8/D8-M8))*100 | V8: MBU26 sheet: AD16 petrol VKT | AD10 conventional | AD12 BEV | AD14 PHEV
A9: 2029 | B9: =SUM('4. Engine forecasts'!G18:G21) | C9: =SUM('4. Engine forecasts'!I18:I21) | D9: =B9+C9 | E9: 32608.441 | F9: 13926.561 | G9: 2502.1796 | H9: 1394.2015 | I9: =SUM(E9:H9) | J9: =E9/I9 | K9: =F9/I9 | L9: =G9/I9 | M9: =H9/I9 | N9: =D9*(L9+M9) | O9: 0.36301897 | P9: =D9*L9 | Q9: =D9*M9 | R9: =B9-(1-O9)*N9 | S9: =C9-O9*N9 | T9: =P9+Q9+R9+S9-D9 | U9: =MAX(ABS(R9/D9-J9),ABS(S9/D9-K9),ABS(P9/D9-L9),ABS(Q9/D9-M9))*100 | V9: MBU26 sheet: AE16 petrol VKT | AE10 conventional | AE12 BEV | AE14 PHEV
A10: 2030 | B10: =SUM('4. Engine forecasts'!G22:G25) | C10: =SUM('4. Engine forecasts'!I22:I25) | D10: =B10+C10 | E10: 32869.872 | F10: 14402.438 | G10: 3074.1364 | H10: 1688.918 | I10: =SUM(E10:H10) | J10: =E10/I10 | K10: =F10/I10 | L10: =G10/I10 | M10: =H10/I10 | N10: =D10*(L10+M10) | O10: 0.3729654 | P10: =D10*L10 | Q10: =D10*M10 | R10: =B10-(1-O10)*N10 | S10: =C10-O10*N10 | T10: =P10+Q10+R10+S10-D10 | U10: =MAX(ABS(R10/D10-J10),ABS(S10/D10-K10),ABS(P10/D10-L10),ABS(Q10/D10-M10))*100 | V10: MBU26 sheet: AF16 petrol VKT | AF10 conventional | AF12 BEV | AF14 PHEV
A11: 2031 | B11: =SUM('4. Engine forecasts'!G26:G29) | C11: =SUM('4. Engine forecasts'!I26:I29) | D11: =B11+C11 | E11: 32608.006 | F11: 14246.193 | G11: 3699.272 | H11: 1982.3012 | I11: =SUM(E11:H11) | J11: =E11/I11 | K11: =F11/I11 | L11: =G11/I11 | M11: =H11/I11 | N11: =D11*(L11+M11) | O11: 0.38263714 | P11: =D11*L11 | Q11: =D11*M11 | R11: =B11-(1-O11)*N11 | S11: =C11-O11*N11 | T11: =P11+Q11+R11+S11-D11 | U11: =MAX(ABS(R11/D11-J11),ABS(S11/D11-K11),ABS(P11/D11-L11),ABS(Q11/D11-M11))*100 | V11: MBU26 sheet: AG16 petrol VKT | AG10 conventional | AG12 BEV | AG14 PHEV
A12: 2032 | B12: =SUM('4. Engine forecasts'!G30:G33) | C12: =SUM('4. Engine forecasts'!I30:I33) | D12: =B12+C12 | E12: 32257.302 | F12: 14040.969 | G12: 4398.0271 | H12: 2294.2384 | I12: =SUM(E12:H12) | J12: =E12/I12 | K12: =F12/I12 | L12: =G12/I12 | M12: =H12/I12 | N12: =D12*(L12+M12) | O12: 0.39186595 | P12: =D12*L12 | Q12: =D12*M12 | R12: =B12-(1-O12)*N12 | S12: =C12-O12*N12 | T12: =P12+Q12+R12+S12-D12 | U12: =MAX(ABS(R12/D12-J12),ABS(S12/D12-K12),ABS(P12/D12-L12),ABS(Q12/D12-M12))*100 | V12: MBU26 sheet: AH16 petrol VKT | AH10 conventional | AH12 BEV | AH14 PHEV
A13: 2033 | B13: =SUM('4. Engine forecasts'!G34:G37) | C13: =SUM('4. Engine forecasts'!I34:I37) | D13: =B13+C13 | E13: 31744.933 | F13: 13782.702 | G13: 5198.2508 | H13: 2610.7524 | I13: =SUM(E13:H13) | J13: =E13/I13 | K13: =F13/I13 | L13: =G13/I13 | M13: =H13/I13 | N13: =D13*(L13+M13) | O13: 0.40043621 | P13: =D13*L13 | Q13: =D13*M13 | R13: =B13-(1-O13)*N13 | S13: =C13-O13*N13 | T13: =P13+Q13+R13+S13-D13 | U13: =MAX(ABS(R13/D13-J13),ABS(S13/D13-K13),ABS(P13/D13-L13),ABS(Q13/D13-M13))*100 | V13: MBU26 sheet: AI16 petrol VKT | AI10 conventional | AI12 BEV | AI14 PHEV
A14: 2034 | B14: =SUM('4. Engine forecasts'!G38:G41) | C14: =SUM('4. Engine forecasts'!I38:I41) | D14: =B14+C14 | E14: 31150.871 | F14: 13486.528 | G14: 6169.9696 | H14: 2923.8214 | I14: =SUM(E14:H14) | J14: =E14/I14 | K14: =F14/I14 | L14: =G14/I14 | M14: =H14/I14 | N14: =D14*(L14+M14) | O14: 0.40810871 | P14: =D14*L14 | Q14: =D14*M14 | R14: =B14-(1-O14)*N14 | S14: =C14-O14*N14 | T14: =P14+Q14+R14+S14-D14 | U14: =MAX(ABS(R14/D14-J14),ABS(S14/D14-K14),ABS(P14/D14-L14),ABS(Q14/D14-M14))*100 | V14: MBU26 sheet: AJ16 petrol VKT | AJ10 conventional | AJ12 BEV | AJ14 PHEV
A15: 2035 | B15: =SUM('4. Engine forecasts'!G42:G45) | C15: =SUM('4. Engine forecasts'!I42:I45) | D15: =B15+C15 | E15: 30425.364 | F15: 13152.781 | G15: 7342.7065 | H15: 3221.1002 | I15: =SUM(E15:H15) | J15: =E15/I15 | K15: =F15/I15 | L15: =G15/I15 | M15: =H15/I15 | N15: =D15*(L15+M15) | O15: 0.41464806 | P15: =D15*L15 | Q15: =D15*M15 | R15: =B15-(1-O15)*N15 | S15: =C15-O15*N15 | T15: =P15+Q15+R15+S15-D15 | U15: =MAX(ABS(R15/D15-J15),ABS(S15/D15-K15),ABS(P15/D15-L15),ABS(Q15/D15-M15))*100 | V15: MBU26 sheet: AK16 petrol VKT | AK10 conventional | AK12 BEV | AK14 PHEV
A16: 2036 | B16: =SUM('4. Engine forecasts'!G46:G49) | C16: =SUM('4. Engine forecasts'!I46:I49) | D16: =B16+C16 | E16: 29533.962 | F16: 12784.936 | G16: 8722.4254 | H16: 3458.9885 | I16: =SUM(E16:H16) | J16: =E16/I16 | K16: =F16/I16 | L16: =G16/I16 | M16: =H16/I16 | N16: =D16*(L16+M16) | O16: 0.41985409 | P16: =D16*L16 | Q16: =D16*M16 | R16: =B16-(1-O16)*N16 | S16: =C16-O16*N16 | T16: =P16+Q16+R16+S16-D16 | U16: =MAX(ABS(R16/D16-J16),ABS(S16/D16-K16),ABS(P16/D16-L16),ABS(Q16/D16-M16))*100 | V16: MBU26 sheet: AL16 petrol VKT | AL10 conventional | AL12 BEV | AL14 PHEV
A17: 2037 | B17: =SUM('4. Engine forecasts'!G50:G53) | C17: =SUM('4. Engine forecasts'!I50:I53) | D17: =B17+C17 | E17: 28482.925 | F17: 12371.402 | G17: 10347.767 | H17: 3633.9232 | I17: =SUM(E17:H17) | J17: =E17/I17 | K17: =F17/I17 | L17: =G17/I17 | M17: =H17/I17 | N17: =D17*(L17+M17) | O17: 0.42359154 | P17: =D17*L17 | Q17: =D17*M17 | R17: =B17-(1-O17)*N17 | S17: =C17-O17*N17 | T17: =P17+Q17+R17+S17-D17 | U17: =MAX(ABS(R17/D17-J17),ABS(S17/D17-K17),ABS(P17/D17-L17),ABS(Q17/D17-M17))*100 | V17: MBU26 sheet: AM16 petrol VKT | AM10 conventional | AM12 BEV | AM14 PHEV
A18: 2038 | B18: =SUM('4. Engine forecasts'!G54:G57) | C18: =SUM('4. Engine forecasts'!I54:I57) | D18: =B18+C18 | E18: 27247.36 | F18: 11896.569 | G18: 12209.69 | H18: 3757.9993 | I18: =SUM(E18:H18) | J18: =E18/I18 | K18: =F18/I18 | L18: =G18/I18 | M18: =H18/I18 | N18: =D18*(L18+M18) | O18: 0.42581239 | P18: =D18*L18 | Q18: =D18*M18 | R18: =B18-(1-O18)*N18 | S18: =C18-O18*N18 | T18: =P18+Q18+R18+S18-D18 | U18: =MAX(ABS(R18/D18-J18),ABS(S18/D18-K18),ABS(P18/D18-L18),ABS(Q18/D18-M18))*100 | V18: MBU26 sheet: AN16 petrol VKT | AN10 conventional | AN12 BEV | AN14 PHEV
A19: 2039 | B19: =SUM('4. Engine forecasts'!G58:G61) | C19: =SUM('4. Engine forecasts'!I58:I61) | D19: =B19+C19 | E19: 25851.548 | F19: 11374.939 | G19: 14357.699 | H19: 3866.7541 | I19: =SUM(E19:H19) | J19: =E19/I19 | K19: =F19/I19 | L19: =G19/I19 | M19: =H19/I19 | N19: =D19*(L19+M19) | O19: 0.42656805 | P19: =D19*L19 | Q19: =D19*M19 | R19: =B19-(1-O19)*N19 | S19: =C19-O19*N19 | T19: =P19+Q19+R19+S19-D19 | U19: =MAX(ABS(R19/D19-J19),ABS(S19/D19-K19),ABS(P19/D19-L19),ABS(Q19/D19-M19))*100 | V19: MBU26 sheet: AO16 petrol VKT | AO10 conventional | AO12 BEV | AO14 PHEV
A20: 2040 | B20: =SUM('4. Engine forecasts'!G62:G65) | C20: =SUM('4. Engine forecasts'!I62:I65) | D20: =B20+C20 | E20: 24332.996 | F20: 10822.476 | G20: 16789.706 | H20: 3908.9023 | I20: =SUM(E20:H20) | J20: =E20/I20 | K20: =F20/I20 | L20: =G20/I20 | M20: =H20/I20 | N20: =D20*(L20+M20) | O20: 0.4260138 | P20: =D20*L20 | Q20: =D20*M20 | R20: =B20-(1-O20)*N20 | S20: =C20-O20*N20 | T20: =P20+Q20+R20+S20-D20 | U20: =MAX(ABS(R20/D20-J20),ABS(S20/D20-K20),ABS(P20/D20-L20),ABS(Q20/D20-M20))*100 | V20: MBU26 sheet: AP16 petrol VKT | AP10 conventional | AP12 BEV | AP14 PHEV
A21: 2041 | B21: =SUM('4. Engine forecasts'!G66:G69) | C21: =SUM('4. Engine forecasts'!I66:I69) | D21: =B21+C21 | E21: 22722.06 | F21: 10279.171 | G21: 19398.231 | H21: 3858.4033 | I21: =SUM(E21:H21) | J21: =E21/I21 | K21: =F21/I21 | L21: =G21/I21 | M21: =H21/I21 | N21: =D21*(L21+M21) | O21: 0.42440087 | P21: =D21*L21 | Q21: =D21*M21 | R21: =B21-(1-O21)*N21 | S21: =C21-O21*N21 | T21: =P21+Q21+R21+S21-D21 | U21: =MAX(ABS(R21/D21-J21),ABS(S21/D21-K21),ABS(P21/D21-L21),ABS(Q21/D21-M21))*100 | V21: MBU26 sheet: AQ16 petrol VKT | AQ10 conventional | AQ12 BEV | AQ14 PHEV
A22: 2042 | B22: =SUM('4. Engine forecasts'!G70:G73) | C22: =SUM('4. Engine forecasts'!I70:I73) | D22: =B22+C22 | E22: 20913.516 | F22: 9708.6542 | G22: 22141.173 | H22: 3783.3597 | I22: =SUM(E22:H22) | J22: =E22/I22 | K22: =F22/I22 | L22: =G22/I22 | M22: =H22/I22 | N22: =D22*(L22+M22) | O22: 0.42205896 | P22: =D22*L22 | Q22: =D22*M22 | R22: =B22-(1-O22)*N22 | S22: =C22-O22*N22 | T22: =P22+Q22+R22+S22-D22 | U22: =MAX(ABS(R22/D22-J22),ABS(S22/D22-K22),ABS(P22/D22-L22),ABS(Q22/D22-M22))*100 | V22: MBU26 sheet: AR16 petrol VKT | AR10 conventional | AR12 BEV | AR14 PHEV
A23: 2043 | B23: =SUM('4. Engine forecasts'!G74:G77) | C23: =SUM('4. Engine forecasts'!I74:I77) | D23: =B23+C23 | E23: 19088.973 | F23: 9162.1241 | G23: 24856.286 | H23: 3690.8605 | I23: =SUM(E23:H23) | J23: =E23/I23 | K23: =F23/I23 | L23: =G23/I23 | M23: =H23/I23 | N23: =D23*(L23+M23) | O23: 0.41936566 | P23: =D23*L23 | Q23: =D23*M23 | R23: =B23-(1-O23)*N23 | S23: =C23-O23*N23 | T23: =P23+Q23+R23+S23-D23 | U23: =MAX(ABS(R23/D23-J23),ABS(S23/D23-K23),ABS(P23/D23-L23),ABS(Q23/D23-M23))*100 | V23: MBU26 sheet: AS16 petrol VKT | AS10 conventional | AS12 BEV | AS14 PHEV
A24: 2044 | B24: =SUM('4. Engine forecasts'!G78:G81) | C24: =SUM('4. Engine forecasts'!I78:I81) | D24: =B24+C24 | E24: 17355.347 | F24: 8641.1714 | G24: 27364.06 | H24: 3587.8426 | I24: =SUM(E24:H24) | J24: =E24/I24 | K24: =F24/I24 | L24: =G24/I24 | M24: =H24/I24 | N24: =D24*(L24+M24) | O24: 0.41668813 | P24: =D24*L24 | Q24: =D24*M24 | R24: =B24-(1-O24)*N24 | S24: =C24-O24*N24 | T24: =P24+Q24+R24+S24-D24 | U24: =MAX(ABS(R24/D24-J24),ABS(S24/D24-K24),ABS(P24/D24-L24),ABS(Q24/D24-M24))*100 | V24: MBU26 sheet: AT16 petrol VKT | AT10 conventional | AT12 BEV | AT14 PHEV
A25: 2045 | B25: =SUM('4. Engine forecasts'!G82:G85) | C25: =SUM('4. Engine forecasts'!I82:I85) | D25: =B25+C25 | E25: 15742.737 | F25: 8152.9592 | G25: 29735.47 | H25: 3475.4088 | I25: =SUM(E25:H25) | J25: =E25/I25 | K25: =F25/I25 | L25: =G25/I25 | M25: =H25/I25 | N25: =D25*(L25+M25) | O25: 0.414319 | P25: =D25*L25 | Q25: =D25*M25 | R25: =B25-(1-O25)*N25 | S25: =C25-O25*N25 | T25: =P25+Q25+R25+S25-D25 | U25: =MAX(ABS(R25/D25-J25),ABS(S25/D25-K25),ABS(P25/D25-L25),ABS(Q25/D25-M25))*100 | V25: MBU26 sheet: AU16 petrol VKT | AU10 conventional | AU12 BEV | AU14 PHEV
A26: 2046 | B26: =SUM('4. Engine forecasts'!G86:G89) | C26: =SUM('4. Engine forecasts'!I86:I89) | D26: =B26+C26 | E26: 14266.194 | F26: 7688.0732 | G26: 32156.359 | H26: 3358.808 | I26: =SUM(E26:H26) | J26: =E26/I26 | K26: =F26/I26 | L26: =G26/I26 | M26: =H26/I26 | N26: =D26*(L26+M26) | O26: 0.4124371 | P26: =D26*L26 | Q26: =D26*M26 | R26: =B26-(1-O26)*N26 | S26: =C26-O26*N26 | T26: =P26+Q26+R26+S26-D26 | U26: =MAX(ABS(R26/D26-J26),ABS(S26/D26-K26),ABS(P26/D26-L26),ABS(Q26/D26-M26))*100 | V26: MBU26 sheet: AV16 petrol VKT | AV10 conventional | AV12 BEV | AV14 PHEV
A27: 2047 | B27: =SUM('4. Engine forecasts'!G90:G93) | C27: =SUM('4. Engine forecasts'!I90:I93) | D27: =B27+C27 | E27: 12918.02 | F27: 7243.4554 | G27: 34537.073 | H27: 3243.2278 | I27: =SUM(E27:H27) | J27: =E27/I27 | K27: =F27/I27 | L27: =G27/I27 | M27: =H27/I27 | N27: =D27*(L27+M27) | O27: 0.41109394 | P27: =D27*L27 | Q27: =D27*M27 | R27: =B27-(1-O27)*N27 | S27: =C27-O27*N27 | T27: =P27+Q27+R27+S27-D27 | U27: =MAX(ABS(R27/D27-J27),ABS(S27/D27-K27),ABS(P27/D27-L27),ABS(Q27/D27-M27))*100 | V27: MBU26 sheet: AW16 petrol VKT | AW10 conventional | AW12 BEV | AW14 PHEV
A28: 2048 | B28: =SUM('4. Engine forecasts'!G94:G97) | C28: =SUM('4. Engine forecasts'!I94:I97) | D28: =B28+C28 | E28: 11705.987 | F28: 6815.9425 | G28: 36975.108 | H28: 3136.5232 | I28: =SUM(E28:H28) | J28: =E28/I28 | K28: =F28/I28 | L28: =G28/I28 | M28: =H28/I28 | N28: =D28*(L28+M28) | O28: 0.41022951 | P28: =D28*L28 | Q28: =D28*M28 | R28: =B28-(1-O28)*N28 | S28: =C28-O28*N28 | T28: =P28+Q28+R28+S28-D28 | U28: =MAX(ABS(R28/D28-J28),ABS(S28/D28-K28),ABS(P28/D28-L28),ABS(Q28/D28-M28))*100 | V28: MBU26 sheet: AX16 petrol VKT | AX10 conventional | AX12 BEV | AX14 PHEV
A29: 2049 | B29: =SUM('4. Engine forecasts'!G98:G101) | C29: =SUM('4. Engine forecasts'!I98:I101) | D29: =B29+C29 | E29: 10602.923 | F29: 6401.3158 | G29: 39221.492 | H29: 3026.8632 | I29: =SUM(E29:H29) | J29: =E29/I29 | K29: =F29/I29 | L29: =G29/I29 | M29: =H29/I29 | N29: =D29*(L29+M29) | O29: 0.40972049 | P29: =D29*L29 | Q29: =D29*M29 | R29: =B29-(1-O29)*N29 | S29: =C29-O29*N29 | T29: =P29+Q29+R29+S29-D29 | U29: =MAX(ABS(R29/D29-J29),ABS(S29/D29-K29),ABS(P29/D29-L29),ABS(Q29/D29-M29))*100 | V29: MBU26 sheet: AY16 petrol VKT | AY10 conventional | AY12 BEV | AY14 PHEV
A30: 2050 | B30: =SUM('4. Engine forecasts'!G102:G105) | C30: =SUM('4. Engine forecasts'!I102:I105) | D30: =B30+C30 | E30: 9598.8589 | F30: 6001.2039 | G30: 41168.801 | H30: 2910.0433 | I30: =SUM(E30:H30) | J30: =E30/I30 | K30: =F30/I30 | L30: =G30/I30 | M30: =H30/I30 | N30: =D30*(L30+M30) | O30: 0.40946745 | P30: =D30*L30 | Q30: =D30*M30 | R30: =B30-(1-O30)*N30 | S30: =C30-O30*N30 | T30: =P30+Q30+R30+S30-D30 | U30: =MAX(ABS(R30/D30-J30),ABS(S30/D30-K30),ABS(P30/D30-L30),ABS(Q30/D30-M30))*100 | V30: MBU26 sheet: AZ16 petrol VKT | AZ10 conventional | AZ12 BEV | AZ14 PHEV
A32: The 'EV switch drawn from RUC pool' column is this workbook's single allocation assumption: of each year's electric-vehicle kilometres, that fraction is deducted from the light RUC pool and the remainder from the petrol pool. It was chosen once so the combined mix tracks MoT's class proportions smoothly - the 'largest gap to MoT mix' column shows the result stays within a fraction of a share point of MoT's official mix. Change the assumption and every downstream number re-computes.

Sheet 6. Rates & revenue
A1: From kilometres to dollars
A2: Rates are not invented: every effective rate is MoT's own revenue divided by MoT's own volume for the same June year, so legislated changes (including the FY2027/28 petrol duty increases) are embedded automatically. Our kilometres x MoT's effective rates = our revenue.
A4: Per June year. Green = linked; blue = MBU26 official inputs (source cells at right)
A5: June year | B5: MoT petrol litres (million L) | C5: MoT petrol VKT (million km) | D5: Fuel intensity (L/100km) = litres/VKT x 100 | E5: MoT petrol duty revenue ($m) | F5: Effective duty rate ($/litre) = revenue/litres | G5: Our petrol km (million) | H5: Our petrol litres = km x intensity / 100 | I5: Petrol duty revenue ($m) = litres x rate | J5: MoT conventional RUC revenue ($m) | K5: Conventional rate ($/km) | L5: Our conventional km | M5: Conventional RUC revenue ($m) | N5: MoT BEV RUC revenue ($m) | O5: BEV rate ($/km) | P5: Our BEV km | Q5: BEV RUC revenue ($m) | R5: MoT PHEV RUC revenue ($m) | S5: PHEV rate ($/km) | T5: Our PHEV km | U5: PHEV RUC revenue ($m) | V5: MoT heavy RUC revenue ($m) | W5: MoT heavy km / heavy rate ($/km) | X5: Our heavy km | Y5: Heavy RUC revenue ($m)
A6: 2026 | B6: 2945.8253 | C6: ='5. Light fleet split'!E6 | D6: =B6/C6*100 | E6: 2062.7847 | F6: =E6/B6 | G6: ='5. Light fleet split'!R6 | H6: =G6*D6/100 | I6: =H6*F6 | J6: 873.81597 | K6: =J6/'5. Light fleet split'!F6 | L6: ='5. Light fleet split'!S6 | M6: =L6*K6 | N6: 81.464807 | O6: =N6/'5. Light fleet split'!G6 | P6: ='5. Light fleet split'!P6 | Q6: =P6*O6 | R6: 21.840321 | S6: =R6/'5. Light fleet split'!H6 | T6: ='5. Light fleet split'!Q6 | U6: =T6*S6 | V6: 1146.5048 | W6: 4106.6571 | X6: =SUM('4. Engine forecasts'!K6:K9) | Y6: =X6*V6/W6
A7: 2027 | B7: 2896.4894 | C7: ='5. Light fleet split'!E7 | D7: =B7/C7*100 | E7: 2200.8779 | F7: =E7/B7 | G7: ='5. Light fleet split'!R7 | H7: =G7*D7/100 | I7: =H7*F7 | J7: 943.71699 | K7: =J7/'5. Light fleet split'!F7 | L7: ='5. Light fleet split'!S7 | M7: =L7*K7 | N7: 114.63412 | O7: =N7/'5. Light fleet split'!G7 | P7: ='5. Light fleet split'!P7 | Q7: =P7*O7 | R7: 31.708186 | S7: =R7/'5. Light fleet split'!H7 | T7: ='5. Light fleet split'!Q7 | U7: =T7*S7 | V7: 1278.2183 | W7: 4256.1427 | X7: =SUM('4. Engine forecasts'!K10:K13) | Y7: =X7*V7/W7
A8: 2028 | B8: 2889.1389 | C8: ='5. Light fleet split'!E8 | D8: =B8/C8*100 | E8: 2456.0264 | F8: =E8/B8 | G8: ='5. Light fleet split'!R8 | H8: =G8*D8/100 | I8: =H8*F8 | J8: 1091.8365 | K8: =J8/'5. Light fleet split'!F8 | L8: ='5. Light fleet split'!S8 | M8: =L8*K8 | N8: 161.83574 | O8: =N8/'5. Light fleet split'!G8 | P8: ='5. Light fleet split'!P8 | Q8: =P8*O8 | R8: 44.693725 | S8: =R8/'5. Light fleet split'!H8 | T8: ='5. Light fleet split'!Q8 | U8: =T8*S8 | V8: 1443.3124 | W8: 4323.4201 | X8: =SUM('4. Engine forecasts'!K14:K17) | Y8: =X8*V8/W8
A9: 2029 | B9: 2884.1152 | C9: ='5. Light fleet split'!E9 | D9: =B9/C9*100 | E9: 2596.023 | F9: =E9/B9 | G9: ='5. Light fleet split'!R9 | H9: =G9*D9/100 | I9: =H9*F9 | J9: 1199.4093 | K9: =J9/'5. Light fleet split'!F9 | L9: ='5. Light fleet split'!S9 | M9: =L9*K9 | N9: 215.52524 | O9: =N9/'5. Light fleet split'!G9 | P9: ='5. Light fleet split'!P9 | Q9: =P9*O9 | R9: 59.21871 | S9: =R9/'5. Light fleet split'!H9 | T9: ='5. Light fleet split'!Q9 | U9: =T9*S9 | V9: 1555.6697 | W9: 4400.6752 | X9: =SUM('4. Engine forecasts'!K18:K21) | Y9: =X9*V9/W9
A10: 2030 | B10: 2878.5933 | C10: ='5. Light fleet split'!E10 | D10: =B10/C10*100 | E10: 2706.1635 | F10: =E10/B10 | G10: ='5. Light fleet split'!R10 | H10: =G10*D10/100 | I10: =H10*F10 | J10: 1295.559 | K10: =J10/'5. Light fleet split'!F10 | L10: ='5. Light fleet split'!S10 | M10: =L10*K10 | N10: 276.56468 | O10: =N10/'5. Light fleet split'!G10 | P10: ='5. Light fleet split'!P10 | Q10: =P10*O10 | R10: 74.928848 | S10: =R10/'5. Light fleet split'!H10 | T10: ='5. Light fleet split'!Q10 | U10: =T10*S10 | V10: 1652.123 | W10: 4474.7037 | X10: =SUM('4. Engine forecasts'!K22:K25) | Y10: =X10*V10/W10
A11: 2031 | B11: 2827.2564 | C11: ='5. Light fleet split'!E11 | D11: =B11/C11*100 | E11: 2771.0709 | F11: =E11/B11 | G11: ='5. Light fleet split'!R11 | H11: =G11*D11/100 | I11: =H11*F11 | J11: 1336.1505 | K11: =J11/'5. Light fleet split'!F11 | L11: ='5. Light fleet split'!S11 | M11: =L11*K11 | N11: 346.95472 | O11: =N11/'5. Light fleet split'!G11 | P11: ='5. Light fleet split'!P11 | Q11: =P11*O11 | R11: 91.691344 | S11: =R11/'5. Light fleet split'!H11 | T11: ='5. Light fleet split'!Q11 | U11: =T11*S11 | V11: 1724.9352 | W11: 4480.7585 | X11: =SUM('4. Engine forecasts'!K26:K29) | Y11: =X11*V11/W11
A12: 2032 | B12: 2768.7398 | C12: ='5. Light fleet split'!E12 | D12: =B12/C12*100 | E12: 2824.5047 | F12: =E12/B12 | G12: ='5. Light fleet split'!R12 | H12: =G12*D12/100 | I12: =H12*F12 | J12: 1370.6092 | K12: =J12/'5. Light fleet split'!F12 | L12: ='5. Light fleet split'!S12 | M12: =L12*K12 | N12: 429.31341 | O12: =N12/'5. Light fleet split'!G12 | P12: ='5. Light fleet split'!P12 | Q12: =P12*O12 | R12: 110.44464 | S12: =R12/'5. Light fleet split'!H12 | T12: ='5. Light fleet split'!Q12 | U12: =T12*S12 | V12: 1795.7546 | W12: 4481.8235 | X12: =SUM('4. Engine forecasts'!K30:K33) | Y12: =X12*V12/W12
A13: 2033 | B13: 2697.1043 | C13: ='5. Light fleet split'!E13 | D13: =B13/C13*100 | E13: 2859.327 | F13: =E13/B13 | G13: ='5. Light fleet split'!R13 | H13: =G13*D13/100 | I13: =H13*F13 | J13: 1398.1862 | K13: =J13/'5. Light fleet split'!F13 | L13: ='5. Light fleet split'!S13 | M13: =L13*K13 | N13: 527.33655 | O13: =N13/'5. Light fleet split'!G13 | P13: ='5. Light fleet split'!P13 | Q13: =P13*O13 | R13: 130.60289 | S13: =R13/'5. Light fleet split'!H13 | T13: ='5. Light fleet split'!Q13 | U13: =T13*S13 | V13: 1864.4834 | W13: 4477.8408 | X13: =SUM('4. Engine forecasts'!K34:K37) | Y13: =X13*V13/W13
A14: 2034 | B14: 2619.4888 | C14: ='5. Light fleet split'!E14 | D14: =B14/C14*100 | E14: 2881.8095 | F14: =E14/B14 | G14: ='5. Light fleet split'!R14 | H14: =G14*D14/100 | I14: =H14*F14 | J14: 1419.7942 | K14: =J14/'5. Light fleet split'!F14 | L14: ='5. Light fleet split'!S14 | M14: =L14*K14 | N14: 649.54355 | O14: =N14/'5. Light fleet split'!G14 | P14: ='5. Light fleet split'!P14 | Q14: =P14*O14 | R14: 151.79019 | S14: =R14/'5. Light fleet split'!H14 | T14: ='5. Light fleet split'!Q14 | U14: =T14*S14 | V14: 1927.2334 | W14: 4460.3108 | X14: =SUM('4. Engine forecasts'!K38:K41) | Y14: =X14*V14/W14
A15: 2035 | B15: 2531.9752 | C15: ='5. Light fleet split'!E15 | D15: =B15/C15*100 | E15: 2886.6932 | F15: =E15/B15 | G15: ='5. Light fleet split'!R15 | H15: =G15*D15/100 | I15: =H15*F15 | J15: 1434.9684 | K15: =J15/'5. Light fleet split'!F15 | L15: ='5. Light fleet split'!S15 | M15: =L15*K15 | N15: 801.08928 | O15: =N15/'5. Light fleet split'!G15 | P15: ='5. Light fleet split'!P15 | Q15: =P15*O15 | R15: 173.29519 | S15: =R15/'5. Light fleet split'!H15 | T15: ='5. Light fleet split'!Q15 | U15: =T15*S15 | V15: 1984.3156 | W15: 4431.3036 | X15: =SUM('4. Engine forecasts'!K42:K45) | Y15: =X15*V15/W15
A16: 2036 | B16: 2432.0655 | C16: ='5. Light fleet split'!E16 | D16: =B16/C16*100 | E16: 2870.0202 | F16: =E16/B16 | G16: ='5. Light fleet split'!R16 | H16: =G16*D16/100 | I16: =H16*F16 | J16: 1443.7389 | K16: =J16/'5. Light fleet split'!F16 | L16: ='5. Light fleet split'!S16 | M16: =L16*K16 | N16: 984.97989 | O16: =N16/'5. Light fleet split'!G16 | P16: ='5. Light fleet split'!P16 | Q16: =P16*O16 | R16: 192.61378 | S16: =R16/'5. Light fleet split'!H16 | T16: ='5. Light fleet split'!Q16 | U16: =T16*S16 | V16: 2039.8779 | W16: 4400.9836 | X16: =SUM('4. Engine forecasts'!K46:K49) | Y16: =X16*V16/W16
A17: 2037 | B17: 2320.7043 | C17: ='5. Light fleet split'!E17 | D17: =B17/C17*100 | E17: 2831.3485 | F17: =E17/B17 | G17: ='5. Light fleet split'!R17 | H17: =G17*D17/100 | I17: =H17*F17 | J17: 1444.423 | K17: =J17/'5. Light fleet split'!F17 | L17: ='5. Light fleet split'!S17 | M17: =L17*K17 | N17: 1208.1535 | O17: =N17/'5. Light fleet split'!G17 | P17: ='5. Light fleet split'!P17 | Q17: =P17*O17 | R17: 209.22313 | S17: =R17/'5. Light fleet split'!H17 | T17: ='5. Light fleet split'!Q17 | U17: =T17*S17 | V17: 2092.9457 | W17: 4367.4462 | X17: =SUM('4. Engine forecasts'!K50:K53) | Y17: =X17*V17/W17
A18: 2038 | B18: 2196.3022 | C18: ='5. Light fleet split'!E18 | D18: =B18/C18*100 | E18: 2767.3649 | F18: =E18/B18 | G18: ='5. Light fleet split'!R18 | H18: =G18*D18/100 | I18: =H18*F18 | J18: 1434.5477 | K18: =J18/'5. Light fleet split'!F18 | L18: ='5. Light fleet split'!S18 | M18: =L18*K18 | N18: 1472.3054 | O18: =N18/'5. Light fleet split'!G18 | P18: ='5. Light fleet split'!P18 | Q18: =P18*O18 | R18: 223.46943 | S18: =R18/'5. Light fleet split'!H18 | T18: ='5. Light fleet split'!Q18 | U18: =T18*S18 | V18: 2143.7937 | W18: 4331.5527 | X18: =SUM('4. Engine forecasts'!K54:K57) | Y18: =X18*V18/W18
A19: 2039 | B19: 2061.2747 | C19: ='5. Light fleet split'!E19 | D19: =B19/C19*100 | E19: 2679.6033 | F19: =E19/B19 | G19: ='5. Light fleet split'!R19 | H19: =G19*D19/100 | I19: =H19*F19 | J19: 1415.1562 | K19: =J19/'5. Light fleet split'!F19 | L19: ='5. Light fleet split'!S19 | M19: =L19*K19 | N19: 1786.2413 | O19: =N19/'5. Light fleet split'!G19 | P19: ='5. Light fleet split'!P19 | Q19: =P19*O19 | R19: 237.22536 | S19: =R19/'5. Light fleet split'!H19 | T19: ='5. Light fleet split'!Q19 | U19: =T19*S19 | V19: 2191.7264 | W19: 4292.1587 | X19: =SUM('4. Engine forecasts'!K58:K61) | Y19: =X19*V19/W19
A20: 2040 | B20: 1918.9971 | C20: ='5. Light fleet split'!E20 | D20: =B20/C20*100 | E20: 2571.2889 | F20: =E20/B20 | G20: ='5. Light fleet split'!R20 | H20: =G20*D20/100 | I20: =H20*F20 | J20: 1387.8202 | K20: =J20/'5. Light fleet split'!F20 | L20: ='5. Light fleet split'!S20 | M20: =L20*K20 | N20: 2153.0279 | O20: =N20/'5. Light fleet split'!G20 | P20: ='5. Light fleet split'!P20 | Q20: =P20*O20 | R20: 247.17944 | S20: =R20/'5. Light fleet split'!H20 | T20: ='5. Light fleet split'!Q20 | U20: =T20*S20 | V20: 2237.0046 | W20: 4250.0728 | X20: =SUM('4. Engine forecasts'!K62:K65) | Y20: =X20*V20/W20
A21: 2041 | B21: 1772.1668 | C21: ='5. Light fleet split'!E21 | D21: =B21/C21*100 | E21: 2445.3294 | F21: =E21/B21 | G21: ='5. Light fleet split'!R21 | H21: =G21*D21/100 | I21: =H21*F21 | J21: 1357.5188 | K21: =J21/'5. Light fleet split'!F21 | L21: ='5. Light fleet split'!S21 | M21: =L21*K21 | N21: 2561.8273 | O21: =N21/'5. Light fleet split'!G21 | P21: ='5. Light fleet split'!P21 | Q21: =P21*O21 | R21: 251.27852 | S21: =R21/'5. Light fleet split'!H21 | T21: ='5. Light fleet split'!Q21 | U21: =T21*S21 | V21: 2280.098 | W21: 4206.3961 | X21: =SUM('4. Engine forecasts'!K66:K69) | Y21: =X21*V21/W21
A22: 2042 | B22: 1612.9036 | C22: ='5. Light fleet split'!E22 | D22: =B22/C22*100 | E22: 2290.0128 | F22: =E22/B22 | G22: ='5. Light fleet split'!R22 | H22: =G22*D22/100 | I22: =H22*F22 | J22: 1319.309 | K22: =J22/'5. Light fleet split'!F22 | L22: ='5. Light fleet split'!S22 | M22: =L22*K22 | N22: 3008.764 | O22: =N22/'5. Light fleet split'!G22 | P22: ='5. Light fleet split'!P22 | Q22: =P22*O22 | R22: 253.54185 | S22: =R22/'5. Light fleet split'!H22 | T22: ='5. Light fleet split'!Q22 | U22: =T22*S22 | V22: 2321.4525 | W22: 4162.0992 | X22: =SUM('4. Engine forecasts'!K70:K73) | Y22: =X22*V22/W22
A23: 2043 | B23: 1455.56 | C23: ='5. Light fleet split'!E23 | D23: =B23/C23*100 | E23: 2124.8629 | F23: =E23/B23 | G23: ='5. Light fleet split'!R23 | H23: =G23*D23/100 | I23: =H23*F23 | J23: 1280.0862 | K23: =J23/'5. Light fleet split'!F23 | L23: ='5. Light fleet split'!S23 | M23: =L23*K23 | N23: 3472.7959 | O23: =N23/'5. Light fleet split'!G23 | P23: ='5. Light fleet split'!P23 | Q23: =P23*O23 | R23: 254.30029 | S23: =R23/'5. Light fleet split'!H23 | T23: ='5. Light fleet split'!Q23 | U23: =T23*S23 | V23: 2359.1013 | W23: 4113.7668 | X23: =SUM('4. Engine forecasts'!K74:K77) | Y23: =X23*V23/W23
A24: 2044 | B24: 1308.2461 | C24: ='5. Light fleet split'!E24 | D24: =B24/C24*100 | E24: 1962.1284 | F24: =E24/B24 | G24: ='5. Light fleet split'!R24 | H24: =G24*D24/100 | I24: =H24*F24 | J24: 1240.3969 | K24: =J24/'5. Light fleet split'!F24 | L24: ='5. Light fleet split'!S24 | M24: =L24*K24 | N24: 3927.974 | O24: =N24/'5. Light fleet split'!G24 | P24: ='5. Light fleet split'!P24 | Q24: =P24*O24 | R24: 253.96544 | S24: =R24/'5. Light fleet split'!H24 | T24: ='5. Light fleet split'!Q24 | U24: =T24*S24 | V24: 2393.8529 | W24: 4063.0592 | X24: =SUM('4. Engine forecasts'!K78:K81) | Y24: =X24*V24/W24
A25: 2045 | B25: 1172.9685 | C25: ='5. Light fleet split'!E25 | D25: =B25/C25*100 | E25: 1806.1194 | F25: =E25/B25 | G25: ='5. Light fleet split'!R25 | H25: =G25*D25/100 | I25: =H25*F25 | J25: 1201.5424 | K25: =J25/'5. Light fleet split'!F25 | L25: ='5. Light fleet split'!S25 | M25: =L25*K25 | N25: 4382.2649 | O25: =N25/'5. Light fleet split'!G25 | P25: ='5. Light fleet split'!P25 | Q25: =P25*O25 | R25: 252.57533 | S25: =R25/'5. Light fleet split'!H25 | T25: ='5. Light fleet split'!Q25 | U25: =T25*S25 | V25: 2425.7699 | W25: 4010.2994 | X25: =SUM('4. Engine forecasts'!K82:K85) | Y25: =X25*V25/W25
A26: 2046 | B26: 1050.5206 | C26: ='5. Light fleet split'!E26 | D26: =B26/C26*100 | E26: 1659.5547 | F26: =E26/B26 | G26: ='5. Light fleet split'!R26 | H26: =G26*D26/100 | I26: =H26*F26 | J26: 1162.4367 | K26: =J26/'5. Light fleet split'!F26 | L26: ='5. Light fleet split'!S26 | M26: =L26*K26 | N26: 4862.0415 | O26: =N26/'5. Light fleet split'!G26 | P26: ='5. Light fleet split'!P26 | Q26: =P26*O26 | R26: 250.44952 | S26: =R26/'5. Light fleet split'!H26 | T26: ='5. Light fleet split'!Q26 | U26: =T26*S26 | V26: 2453.0084 | W26: 3952.6719 | X26: =SUM('4. Engine forecasts'!K86:K89) | Y26: =X26*V26/W26
A27: 2047 | B27: 939.98622 | C27: ='5. Light fleet split'!E27 | D27: =B27/C27*100 | E27: 1522.5137 | F27: =E27/B27 | G27: ='5. Light fleet split'!R27 | H27: =G27*D27/100 | I27: =H27*F27 | J27: 1122.9167 | K27: =J27/'5. Light fleet split'!F27 | L27: ='5. Light fleet split'!S27 | M27: =L27*K27 | N27: 5354.1098 | O27: =N27/'5. Light fleet split'!G27 | P27: ='5. Light fleet split'!P27 | Q27: =P27*O27 | R27: 247.94476 | S27: =R27/'5. Light fleet split'!H27 | T27: ='5. Light fleet split'!Q27 | U27: =T27*S27 | V27: 2476.3115 | W27: 3891.7053 | X27: =SUM('4. Engine forecasts'!K90:K93) | Y27: =X27*V27/W27
A28: 2048 | B28: 841.58928 | C28: ='5. Light fleet split'!E28 | D28: =B28/C28*100 | E28: 1396.8154 | F28: =E28/B28 | G28: ='5. Light fleet split'!R28 | H28: =G28*D28/100 | I28: =H28*F28 | J28: 1082.7465 | K28: =J28/'5. Light fleet split'!F28 | L28: ='5. Light fleet split'!S28 | M28: =L28*K28 | N28: 5873.6808 | O28: =N28/'5. Light fleet split'!G28 | P28: ='5. Light fleet split'!P28 | Q28: =P28*O28 | R28: 245.69954 | S28: =R28/'5. Light fleet split'!H28 | T28: ='5. Light fleet split'!Q28 | U28: =T28*S28 | V28: 2495.5951 | W28: 3827.5118 | X28: =SUM('4. Engine forecasts'!K94:K97) | Y28: =X28*V28/W28
A29: 2049 | B29: 753.04527 | C29: ='5. Light fleet split'!E29 | D29: =B29/C29*100 | E29: 1279.9794 | F29: =E29/B29 | G29: ='5. Light fleet split'!R29 | H29: =G29*D29/100 | I29: =H29*F29 | J29: 1041.3981 | K29: =J29/'5. Light fleet split'!F29 | L29: ='5. Light fleet split'!S29 | M29: =L29*K29 | N29: 6380.7485 | O29: =N29/'5. Light fleet split'!G29 | P29: ='5. Light fleet split'!P29 | Q29: =P29*O29 | R29: 242.8301 | S29: =R29/'5. Light fleet split'!H29 | T29: ='5. Light fleet split'!Q29 | U29: =T29*S29 | V29: 2510.7119 | W29: 3760.0986 | X29: =SUM('4. Engine forecasts'!K98:K101) | Y29: =X29*V29/W29
A30: 2050 | B30: 673.36813 | C30: ='5. Light fleet split'!E30 | D30: =B30/C30*100 | E30: 1171.5082 | F30: =E30/B30 | G30: ='5. Light fleet split'!R30 | H30: =G30*D30/100 | I30: =H30*F30 | J30: 999.26046 | K30: =J30/'5. Light fleet split'!F30 | L30: ='5. Light fleet split'!S30 | M30: =L30*K30 | N30: 6855.017 | O30: =N30/'5. Light fleet split'!G30 | P30: ='5. Light fleet split'!P30 | Q30: =P30*O30 | R30: 238.94365 | S30: =R30/'5. Light fleet split'!H30 | T30: ='5. Light fleet split'!Q30 | U30: =T30*S30 | V30: 2523.105 | W30: 3691.7995 | X30: =SUM('4. Engine forecasts'!K102:K105) | Y30: =X30*V30/W30
A32: MBU26 source cells per year, e.g. FY2030: petrol litres AF15, petrol duty revenue AF45, conventional RUC revenue AF33 / km AF10, BEV AF35/AF12, PHEV AF37/AF14, heavy AF34/AF11 (column letter advances one per June year on the MBU26 sheet). The effective duty rate steps up in FY2027 (+6c legislated) and FY2028 (+12c) because MoT's own revenue line prices the legislated path.

Sheet 7. NLTF rollup
A1: Rolling up to the National Land Transport Fund
A2: Modelled lines (green) plus the MBU26 lines we do not model (blue: LPG/CNG, refunds, admin fees, registration, track-user charge) combine through the standard fund identities.
A4: Per June year, $m nominal ex GST. Blue inputs quote MBU26 rows 36-63
A5: June year | B5: Petrol duty (ours) | C5: LPG (MBU26) | D5: CNG (MBU26) | E5: Gross fuel excise = sum | F5: Fuel refunds (MBU26) | G5: Net fuel excise | H5: Conventional RUC (ours) | I5: BEV RUC (ours) | J5: PHEV RUC (ours) | K5: Heavy RUC (ours) | L5: Heavy BEV RUC (MBU26) | M5: RUC refunds (MBU26) | N5: Gross RUC = sum + refunds back | O5: RUC admin fees (MBU26) | P5: Net RUC | Q5: Registration MR1+MR2 (MBU26) | R5: Registration admin (MBU26) | S5: Registration refunds (MBU26) | T5: Net registration | U5: Certificate of ownership (MBU26) | V5: Track user charge (MBU26) | W5: Total NLTF = net fuel + net RUC + net rego + TUC | X5: Cross-check: gross-to-net identity
A6: 2026 | B6: ='6. Rates & revenue'!I6 | C6: 42.045163 | D6: 0 | E6: =B6+C6+D6 | F6: 73.267525 | G6: =E6-F6 | H6: ='6. Rates & revenue'!M6 | I6: ='6. Rates & revenue'!Q6 | J6: ='6. Rates & revenue'!U6 | K6: ='6. Rates & revenue'!Y6 | L6: 0 | M6: 67.885034 | N6: =SUM(H6:M6) | O6: 34.570871 | P6: =N6-O6-M6 | Q6: 499.55653 | R6: 72.710567 | S6: 1.7167697 | T6: =Q6-R6-S6 | U6: 0 | V6: 17.406077 | W6: =G6+P6+T6+V6 | X6: =(E6+N6+Q6+U6+V6)-(O6+R6+U6)-(F6+M6+S6)-W6
A7: 2027 | B7: ='6. Rates & revenue'!I7 | C7: 42.63269 | D7: 0 | E7: =B7+C7+D7 | F7: 82.104962 | G7: =E7-F7 | H7: ='6. Rates & revenue'!M7 | I7: ='6. Rates & revenue'!Q7 | J7: ='6. Rates & revenue'!U7 | K7: ='6. Rates & revenue'!Y7 | L7: 0 | M7: 79.515851 | N7: =SUM(H7:M7) | O7: 35.737876 | P7: =N7-O7-M7 | Q7: 570.344 | R7: 72.258477 | S7: 1.9357667 | T7: =Q7-R7-S7 | U7: 0 | V7: 17.5579 | W7: =G7+P7+T7+V7 | X7: =(E7+N7+Q7+U7+V7)-(O7+R7+U7)-(F7+M7+S7)-W7
A8: 2028 | B8: ='6. Rates & revenue'!I8 | C8: 42.853377 | D8: 0 | E8: =B8+C8+D8 | F8: 92.111715 | G8: =E8-F8 | H8: ='6. Rates & revenue'!M8 | I8: ='6. Rates & revenue'!Q8 | J8: ='6. Rates & revenue'!U8 | K8: ='6. Rates & revenue'!Y8 | L8: 20.203036 | M8: 92.546742 | N8: =SUM(H8:M8) | O8: 37.789817 | P8: =N8-O8-M8 | Q8: 564.07591 | R8: 71.886174 | S8: 1.939224 | T8: =Q8-R8-S8 | U8: 0 | V8: 17.5579 | W8: =G8+P8+T8+V8 | X8: =(E8+N8+Q8+U8+V8)-(O8+R8+U8)-(F8+M8+S8)-W8
A9: 2029 | B9: ='6. Rates & revenue'!I9 | C9: 43.056547 | D9: 0 | E9: =B9+C9+D9 | F9: 97.830517 | G9: =E9-F9 | H9: ='6. Rates & revenue'!M9 | I9: ='6. Rates & revenue'!Q9 | J9: ='6. Rates & revenue'!U9 | K9: ='6. Rates & revenue'!Y9 | L9: 26.0839 | M9: 102.08891 | N9: =SUM(H9:M9) | O9: 40.091877 | P9: =N9-O9-M9 | Q9: 558.30784 | R9: 71.520571 | S9: 1.9441623 | T9: =Q9-R9-S9 | U9: 0 | V9: 17.5579 | W9: =G9+P9+T9+V9 | X9: =(E9+N9+Q9+U9+V9)-(O9+R9+U9)-(F9+M9+S9)-W9
A10: 2030 | B10: ='6. Rates & revenue'!I10 | C10: 43.244778 | D10: 0 | E10: =B10+C10+D10 | F10: 102.41299 | G10: =E10-F10 | H10: ='6. Rates & revenue'!M10 | I10: ='6. Rates & revenue'!Q10 | J10: ='6. Rates & revenue'!U10 | K10: ='6. Rates & revenue'!Y10 | L10: 32.847769 | M10: 110.93063 | N10: =SUM(H10:M10) | O10: 42.474009 | P10: =N10-O10-M10 | Q10: 553.00318 | R10: 71.168945 | S10: 1.9505133 | T10: =Q10-R10-S10 | U10: 0 | V10: 17.5579 | W10: =G10+P10+T10+V10 | X10: =(E10+N10+Q10+U10+V10)-(O10+R10+U10)-(F10+M10+S10)-W10
A11: 2031 | B11: ='6. Rates & revenue'!I11 | C11: 43.420118 | D11: 0 | E11: =B11+C11+D11 | F11: 105.36212 | G11: =E11-F11 | H11: ='6. Rates & revenue'!M11 | I11: ='6. Rates & revenue'!Q11 | J11: ='6. Rates & revenue'!U11 | K11: ='6. Rates & revenue'!Y11 | L11: 41.011747 | M11: 117.89132 | N11: =SUM(H11:M11) | O11: 41.725688 | P11: =N11-O11-M11 | Q11: 548.12367 | R11: 70.835129 | S11: 1.9581977 | T11: =Q11-R11-S11 | U11: 0 | V11: 17.5579 | W11: =G11+P11+T11+V11 | X11: =(E11+N11+Q11+U11+V11)-(O11+R11+U11)-(F11+M11+S11)-W11
A12: 2032 | B12: ='6. Rates & revenue'!I12 | C12: 43.584222 | D12: 0 | E12: =B12+C12+D12 | F12: 107.81255 | G12: =E12-F12 | H12: ='6. Rates & revenue'!M12 | I12: ='6. Rates & revenue'!Q12 | J12: ='6. Rates & revenue'!U12 | K12: ='6. Rates & revenue'!Y12 | L12: 51.147368 | M12: 124.68196 | N12: =SUM(H12:M12) | O12: 43.08196 | P12: =N12-O12-M12 | Q12: 543.63186 | R12: 70.520734 | S12: 1.9671337 | T12: =Q12-R12-S12 | U12: 0 | V12: 17.5579 | W12: =G12+P12+T12+V12 | X12: =(E12+N12+Q12+U12+V12)-(O12+R12+U12)-(F12+M12+S12)-W12
A13: 2033 | B13: ='6. Rates & revenue'!I13 | C13: 43.738442 | D13: 0 | E13: =B13+C13+D13 | F13: 109.54963 | G13: =E13-F13 | H13: ='6. Rates & revenue'!M13 | I13: ='6. Rates & revenue'!Q13 | J13: ='6. Rates & revenue'!U13 | K13: ='6. Rates & revenue'!Y13 | L13: 63.283981 | M13: 131.7734 | N13: =SUM(H13:M13) | O13: 44.518874 | P13: =N13-O13-M13 | Q13: 539.49234 | R13: 70.226068 | S13: 1.977241 | T13: =Q13-R13-S13 | U13: 0 | V13: 17.5579 | W13: =G13+P13+T13+V13 | X13: =(E13+N13+Q13+U13+V13)-(O13+R13+U13)-(F13+M13+S13)-W13
A14: 2034 | B14: ='6. Rates & revenue'!I14 | C14: 43.883903 | D14: 0 | E14: =B14+C14+D14 | F14: 110.80495 | G14: =E14-F14 | H14: ='6. Rates & revenue'!M14 | I14: ='6. Rates & revenue'!Q14 | J14: ='6. Rates & revenue'!U14 | K14: ='6. Rates & revenue'!Y14 | L14: 76.928519 | M14: 139.31809 | N14: =SUM(H14:M14) | O14: 46.151857 | P14: =N14-O14-M14 | Q14: 535.67226 | R14: 69.950695 | S14: 1.9884434 | T14: =Q14-R14-S14 | U14: 0 | V14: 17.5579 | W14: =G14+P14+T14+V14 | X14: =(E14+N14+Q14+U14+V14)-(O14+R14+U14)-(F14+M14+S14)-W14
A15: 2035 | B15: ='6. Rates & revenue'!I15 | C15: 44.021547 | D15: 0 | E15: =B15+C15+D15 | F15: 111.37562 | G15: =E15-F15 | H15: ='6. Rates & revenue'!M15 | I15: ='6. Rates & revenue'!Q15 | J15: ='6. Rates & revenue'!U15 | K15: ='6. Rates & revenue'!Y15 | L15: 91.951954 | M15: 147.44979 | N15: =SUM(H15:M15) | O15: 48.013836 | P15: =N15-O15-M15 | Q15: 532.14151 | R15: 69.693765 | S15: 2.0006699 | T15: =Q15-R15-S15 | U15: 0 | V15: 17.5579 | W15: =G15+P15+T15+V15 | X15: =(E15+N15+Q15+U15+V15)-(O15+R15+U15)-(F15+M15+S15)-W15
A16: 2036 | B16: ='6. Rates & revenue'!I16 | C16: 44.15217 | D16: 0 | E16: =B16+C16+D16 | F16: 111.10602 | G16: =E16-F16 | H16: ='6. Rates & revenue'!M16 | I16: ='6. Rates & revenue'!Q16 | J16: ='6. Rates & revenue'!U16 | K16: ='6. Rates & revenue'!Y16 | L16: 109.20381 | M16: 156.34567 | N16: =SUM(H16:M16) | O16: 50.06446 | P16: =N16-O16-M16 | Q16: 528.87273 | R16: 69.454212 | S16: 2.0138553 | T16: =Q16-R16-S16 | U16: 0 | V16: 17.5579 | W16: =G16+P16+T16+V16 | X16: =(E16+N16+Q16+U16+V16)-(O16+R16+U16)-(F16+M16+S16)-W16
A17: 2037 | B17: ='6. Rates & revenue'!I17 | C17: 44.276456 | D17: 0 | E17: =B17+C17+D17 | F17: 109.97348 | G17: =E17-F17 | H17: ='6. Rates & revenue'!M17 | I17: ='6. Rates & revenue'!Q17 | J17: ='6. Rates & revenue'!U17 | K17: ='6. Rates & revenue'!Y17 | L17: 128.51124 | M17: 166.11748 | N17: =SUM(H17:M17) | O17: 52.34002 | P17: =N17-O17-M17 | Q17: 525.84112 | R17: 69.230881 | S17: 2.0279395 | T17: =Q17-R17-S17 | U17: 0 | V17: 17.5579 | W17: =G17+P17+T17+V17 | X17: =(E17+N17+Q17+U17+V17)-(O17+R17+U17)-(F17+M17+S17)-W17
... A30: 2050 | B30: ='6. Rates & revenue'!I30 | C30: 45.505461 | D30: 0 | E30: =B30+C30+D30 | F30: 47.953494 | G30: =E30-F30 | H30: ='6. Rates & revenue'!M30 | I30: ='6. Rates & revenue'!Q30 | J30: ='6. Rates & revenue'!U30 | K30: ='6. Rates & revenue'!Y30 | L30: 767.05337 | M30: 360.36169 | N30: =SUM(H30:M30) | O30: 91.103286 | P30: =N30-O30-M30 | Q30: 500.3006 | R30: 67.338793 | S30: 2.2738711 | T30: =Q30-R30-S30 | U30: 0 | V30: 17.5579 | W30: =G30+P30+T30+V30 | X30: =(E30+N30+Q30+U30+V30)-(O30+R30+U30)-(F30+M30+S30)-W30
A32: Gross RUC adds refunds back before netting them off again (MoT's published convention). The cross-check column recomputes total NLTF the official way - total gross revenue minus total admin fees minus total refunds - and must equal zero against the stream-wise rollup.

Sheet 8. Reconciliation
A1: Does this workbook match the dashboard? Yes - to the dollar.
A2: Blue columns are the committed values behind the dashboard charts (AR(1) engine pack, base case). Green columns are this workbook's formulas. Every difference column should read zero.
A4: Workbook vs committed dashboard pack (base case, June years)
B5: Petrol litres (million L) | E5: Petrol duty revenue ($m) | H5: Conventional light RUC km (m km) | K5: Battery-electric RUC km (m km) | N5: Plug-in hybrid RUC km (m km) | Q5: Conventional light RUC revenue ($m) | T5: Battery-electric RUC revenue ($m) | W5: Plug-in hybrid RUC revenue ($m) | Z5: Heavy RUC revenue ($m) | AC5: Net fuel excise ($m) | AF5: Net RUC ($m) | AI5: Total NLTF revenue ($m)
A6: June year | B6: This workbook | C6: Dashboard | D6: Difference | E6: This workbook | F6: Dashboard | G6: Difference | H6: This workbook | I6: Dashboard | J6: Difference | K6: This workbook | L6: Dashboard | M6: Difference | N6: This workbook | O6: Dashboard | P6: Difference | Q6: This workbook | R6: Dashboard | S6: Difference | T6: This workbook | U6: Dashboard | V6: Difference | W6: This workbook | X6: Dashboard | Y6: Difference | Z6: This workbook | AA6: Dashboard | AB6: Difference | AC6: This workbook | AD6: Dashboard | AE6: Difference | AF6: This workbook | AG6: Dashboard | AH6: Difference | AI6: This workbook | AJ6: Dashboard | AK6: Difference
A7: 2026 | B7: ='6. Rates & revenue'!H6 | C7: 2936.2042 | D7: =B7-C7 | E7: ='6. Rates & revenue'!I6 | F7: 2056.0476 | G7: =E7-F7 | H7: ='5. Light fleet split'!S6 | I7: 12354.533 | J7: =H7-I7 | K7: ='5. Light fleet split'!P6 | L7: 1191.8452 | M7: =K7-L7 | N7: ='5. Light fleet split'!Q6 | O7: 624.21099 | P7: =N7-O7 | Q7: ='6. Rates & revenue'!M6 | R7: 836.92411 | S7: =Q7-R7 | T7: ='6. Rates & revenue'!Q6 | U7: 80.283709 | V7: =T7-U7 | W7: ='6. Rates & revenue'!U6 | X7: 21.523675 | Y7: =W7-X7 | Z7: ='6. Rates & revenue'!Y6 | AA7: 1129.3228 | AB7: =Z7-AA7 | AC7: ='7. NLTF rollup'!G6 | AD7: 2024.8253 | AE7: =AC7-AD7 | AF7: ='7. NLTF rollup'!P6 | AG7: 2033.4834 | AH7: =AF7-AG7 | AI7: ='7. NLTF rollup'!W6 | AJ7: 4500.8439 | AK7: =AI7-AJ7
A8: 2027 | B8: ='6. Rates & revenue'!H7 | C8: 2766.7896 | D8: =B8-C8 | E8: ='6. Rates & revenue'!I7 | F8: 2102.3264 | G8: =E8-F8 | H8: ='5. Light fleet split'!S7 | I8: 11872.662 | J8: =H8-I8 | K8: ='5. Light fleet split'!P7 | L8: 1484.7812 | M8: =K8-L8 | N8: ='5. Light fleet split'!Q7 | O8: 818.27885 | P8: =N8-O8 | Q8: ='6. Rates & revenue'!M7 | R8: 865.90011 | S8: =Q8-R8 | T8: ='6. Rates & revenue'!Q7 | U8: 108.26049 | V8: =T8-U8 | W8: ='6. Rates & revenue'!U7 | X8: 29.945219 | Y8: =W8-X8 | Z8: ='6. Rates & revenue'!Y7 | AA8: 1231.4061 | AB8: =Z8-AA8 | AC8: ='7. NLTF rollup'!G7 | AD8: 2062.8541 | AE8: =AC8-AD8 | AF8: ='7. NLTF rollup'!P7 | AG8: 2199.7741 | AH8: =AF8-AG8 | AI8: ='7. NLTF rollup'!W7 | AJ8: 4776.3358 | AK8: =AI8-AJ8
A9: 2028 | B9: ='6. Rates & revenue'!H8 | C9: 2704.6608 | D9: =B9-C9 | E9: ='6. Rates & revenue'!I8 | F9: 2299.2036 | G9: =E9-F9 | H9: ='5. Light fleet split'!S8 | I9: 12321.178 | J9: =H9-I9 | K9: ='5. Light fleet split'!P8 | L9: 1851.5216 | M9: =K9-L9 | N9: ='5. Light fleet split'!Q8 | O9: 1036.9353 | P9: =N9-O9 | Q9: ='6. Rates & revenue'!M8 | R9: 1001.8614 | S9: =Q9-R9 | T9: ='6. Rates & revenue'!Q8 | U9: 150.62129 | V9: =T9-U9 | W9: ='6. Rates & revenue'!U8 | X9: 41.596661 | Y9: =W9-X9 | Z9: ='6. Rates & revenue'!Y8 | AA9: 1380.1167 | AB9: =Z9-AA9 | AC9: ='7. NLTF rollup'!G8 | AD9: 2249.9452 | AE9: =AC9-AD9 | AF9: ='7. NLTF rollup'!P8 | AG9: 2556.6093 | AH9: =AF9-AG9 | AI9: ='7. NLTF rollup'!W8 | AJ9: 5314.3629 | AK9: =AI9-AJ9
A10: 2029 | B10: ='6. Rates & revenue'!H9 | C10: 2655.2717 | D10: =B10-C10 | E10: ='6. Rates & revenue'!I9 | F10: 2390.0385 | G10: =E10-F10 | H10: ='5. Light fleet split'!S9 | I10: 12507.8 | J10: =H10-I10 | K10: ='5. Light fleet split'!P9 | L10: 2286.7714 | M10: =K10-L10 | N10: ='5. Light fleet split'!Q9 | O10: 1274.1772 | P10: =N10-O10 | Q10: ='6. Rates & revenue'!M9 | R10: 1077.2201 | S10: =Q10-R10 | T10: ='6. Rates & revenue'!Q9 | U10: 196.97106 | V10: =T10-U10 | W10: ='6. Rates & revenue'!U9 | X10: 54.120676 | Y10: =W10-X10 | Z10: ='6. Rates & revenue'!Y9 | AA10: 1474.7557 | AB10: =Z10-AA10 | AC10: ='7. NLTF rollup'!G9 | AD10: 2335.2645 | AE10: =AC10-AD10 | AF10: ='7. NLTF rollup'!P9 | AG10: 2789.0596 | AH10: =AF10-AG10 | AI10: ='7. NLTF rollup'!W9 | AJ10: 5626.7251 | AK10: =AI10-AJ10
A11: 2030 | B11: ='6. Rates & revenue'!H10 | C11: 2607.1011 | D11: =B11-C11 | E11: ='6. Rates & revenue'!I10 | F11: 2450.9338 | G11: =E11-F11 | H11: ='5. Light fleet split'!S10 | I11: 12493.298 | J11: =H11-I11 | K11: ='5. Light fleet split'!P10 | L11: 2748.3838 | M11: =K11-L11 | N11: ='5. Light fleet split'!Q10 | O11: 1509.9509 | P11: =N11-O11 | Q11: ='6. Rates & revenue'!M10 | R11: 1123.8239 | S11: =Q11-R11 | T11: ='6. Rates & revenue'!Q10 | U11: 247.25835 | V11: =T11-U11 | W11: ='6. Rates & revenue'!U10 | X11: 66.988971 | Y11: =W11-X11 | Z11: ='6. Rates & revenue'!Y10 | AA11: 1552.689 | AB11: =Z11-AA11 | AC11: ='7. NLTF rollup'!G10 | AD11: 2391.7656 | AE11: =AC11-AD11 | AF11: ='7. NLTF rollup'!P10 | AG11: 2981.1341 | AH11: =AF11-AG11 | AI11: ='7. NLTF rollup'!W10 | AJ11: 5870.3413 | AK11: =AI11-AJ11
A12: 2031 | B12: ='6. Rates & revenue'!H11 | C12: 2551.5349 | D12: =B12-C12 | E12: ='6. Rates & revenue'!I11 | F12: 2500.8287 | G12: =E12-F12 | H12: ='5. Light fleet split'!S11 | I12: 12487.253 | J12: =H12-I12 | K12: ='5. Light fleet split'!P11 | L12: 3309.3272 | M12: =K12-L12 | N12: ='5. Light fleet split'!Q11 | O12: 1773.3444 | P12: =N12-O12 | Q12: ='6. Rates & revenue'!M11 | R12: 1171.1795 | S12: =Q12-R12 | T12: ='6. Rates & revenue'!Q11 | U12: 310.3818 | V12: =T12-U12 | W12: ='6. Rates & revenue'!U11 | X12: 82.026046 | Y12: =W12-X12 | Z12: ='6. Rates & revenue'!Y11 | AA12: 1633.4365 | AB12: =Z12-AA12 | AC12: ='7. NLTF rollup'!G11 | AD12: 2438.8867 | AE12: =AC12-AD12 | AF12: ='7. NLTF rollup'!P11 | AG12: 3196.3099 | AH12: =AF12-AG12 | AI12: ='7. NLTF rollup'!W11 | AJ12: 6128.0849 | AK12: =AI12-AJ12
A13: 2032 | B13: ='6. Rates & revenue'!H12 | C13: 2485.1021 | D13: =B13-C13 | E13: ='6. Rates & revenue'!I12 | F13: 2535.1544 | G13: =E13-F13 | H13: ='5. Light fleet split'!S12 | I13: 12443.786 | J13: =H13-I13 | K13: ='5. Light fleet split'!P12 | L13: 3932.397 | M13: =K13-L13 | N13: ='5. Light fleet split'!Q12 | O13: 2051.3417 | P13: =N13-O13 | Q13: ='6. Rates & revenue'!M12 | R13: 1214.7002 | S13: =Q13-R13 | T13: ='6. Rates & revenue'!Q12 | U13: 383.86093 | V13: =T13-U13 | W13: ='6. Rates & revenue'!U12 | X13: 98.751589 | Y13: =W13-X13 | Z13: ='6. Rates & revenue'!Y12 | AA13: 1712.6277 | AB13: =Z13-AA13 | AC13: ='7. NLTF rollup'!G12 | AD13: 2470.926 | AE13: =AC13-AD13 | AF13: ='7. NLTF rollup'!P12 | AG13: 3418.0058 | AH13: =AF13-AG13 | AI13: ='7. NLTF rollup'!W12 | AJ13: 6377.6338 | AK13: =AI13-AJ13
A14: 2033 | B14: ='6. Rates & revenue'!H13 | C14: 2413.0268 | D14: =B14-C14 | E14: ='6. Rates & revenue'!I13 | F14: 2558.1631 | G14: =E14-F14 | H14: ='5. Light fleet split'!S13 | I14: 12353.374 | J14: =H14-I14 | K14: ='5. Light fleet split'!P13 | L14: 4653.2885 | M14: =K14-L14 | N14: ='5. Light fleet split'!Q13 | O14: 2337.0523 | P14: =N14-O14 | Q14: ='6. Rates & revenue'!M13 | R14: 1253.1881 | S14: =Q14-R14 | T14: ='6. Rates & revenue'!Q13 | U14: 472.05285 | V14: =T14-U14 | W14: ='6. Rates & revenue'!U13 | X14: 116.91104 | Y14: =W14-X14 | Z14: ='6. Rates & revenue'!Y13 | AA14: 1791.0516 | AB14: =Z14-AA14 | AC14: ='7. NLTF rollup'!G13 | AD14: 2492.3519 | AE14: =AC14-AD14 | AF14: ='7. NLTF rollup'!P13 | AG14: 3651.9687 | AH14: =AF14-AG14 | AI14: ='7. NLTF rollup'!W13 | AJ14: 6629.1675 | AK14: =AI14-AJ14
A15: 2034 | B15: ='6. Rates & revenue'!H14 | C15: 2335.199 | D15: =B15-C15 | E15: ='6. Rates & revenue'!I14 | F15: 2569.0504 | G15: =E15-F15 | H15: ='5. Light fleet split'!S14 | I15: 12202.093 | J15: =H15-I15 | K15: ='5. Light fleet split'!P14 | L15: 5525.1261 | M15: =K15-L15 | N15: ='5. Light fleet split'!Q14 | O15: 2618.2433 | P15: =N15-O15 | Q15: ='6. Rates & revenue'!M14 | R15: 1284.5754 | S15: =Q15-R15 | T15: ='6. Rates & revenue'!Q14 | U15: 581.65765 | V15: =T15-U15 | W15: ='6. Rates & revenue'!U14 | X15: 135.9261 | Y15: =W15-X15 | Z15: ='6. Rates & revenue'!Y14 | AA15: 1871.1223 | AB15: =Z15-AA15 | AC15: ='7. NLTF rollup'!G14 | AD15: 2502.1294 | AE15: =AC15-AD15 | AF15: ='7. NLTF rollup'!P14 | AG15: 3904.0581 | AH15: =AF15-AG15 | AI15: ='7. NLTF rollup'!W14 | AJ15: 6887.4785 | AK15: =AI15-AJ15
A16: 2035 | B16: ='6. Rates & revenue'!H15 | C16: 2251.3089 | D16: =B16-C16 | E16: ='6. Rates & revenue'!I15 | F16: 2566.7069 | G16: =E16-F16 | H16: ='5. Light fleet split'!S15 | I16: 11983.806 | J16: =H16-I16 | K16: ='5. Light fleet split'!P15 | L16: 6577.4708 | M16: =K16-L16 | N16: ='5. Light fleet split'!Q15 | O16: 2885.4064 | P16: =N16-O16 | Q16: ='6. Rates & revenue'!M15 | R16: 1307.4332 | S16: =Q16-R16 | T16: ='6. Rates & revenue'!Q15 | U16: 717.60206 | V16: =T16-U16 | W16: ='6. Rates & revenue'!U15 | X16: 155.23487 | Y16: =W16-X16 | Z16: ='6. Rates & revenue'!Y15 | AA16: 1951.6517 | AB16: =Z16-AA16 | AC16: ='7. NLTF rollup'!G15 | AD16: 2499.3528 | AE16: =AC16-AD16 | AF16: ='7. NLTF rollup'!P15 | AG16: 4175.8599 | AH16: =AF16-AG16 | AI16: ='7. NLTF rollup'!W15 | AJ16: 7153.2178 | AK16: =AI16-AJ16
A17: 2036 | B17: ='6. Rates & revenue'!H16 | C17: 2162.0341 | D17: =B17-C17 | E17: ='6. Rates & revenue'!I16 | F17: 2551.3629 | G17: =E17-F17 | H17: ='5. Light fleet split'!S16 | I17: 11707.073 | J17: =H17-I17 | K17: ='5. Light fleet split'!P16 | L17: 7824.3944 | M17: =K17-L17 | N17: ='5. Light fleet split'!Q16 | O17: 3102.8629 | P17: =N17-O17 | Q17: ='6. Rates & revenue'!M16 | R17: 1322.0212 | S17: =Q17-R17 | T17: ='6. Rates & revenue'!Q16 | U17: 883.56974 | V17: =T17-U17 | W17: ='6. Rates & revenue'!U16 | X17: 172.78292 | Y17: =W17-X17 | Z17: ='6. Rates & revenue'!Y16 | AA17: 2031.6756 | AB17: =Z17-AA17 | AC17: ='7. NLTF rollup'!G16 | AD17: 2484.409 | AE17: =AC17-AD17 | AF17: ='7. NLTF rollup'!P16 | AG17: 4469.1888 | AH17: =AF17-AG17 | AI17: ='7. NLTF rollup'!W16 | AJ17: 7428.5604 | AK17: =AI17-AJ17
A18: 2037 | B18: ='6. Rates & revenue'!H17 | C18: 2065.2836 | D18: =B18-C18 | E18: ='6. Rates & revenue'!I17 | F18: 2519.7255 | G18: =E18-F18 | H18: ='5. Light fleet split'!S17 | I18: 11354.384 | J18: =H18-I18 | K18: ='5. Light fleet split'!P17 | L18: 9296.1555 | M18: =K18-L18 | N18: ='5. Light fleet split'!Q17 | O18: 3264.6189 | P18: =N18-O18 | Q18: ='6. Rates & revenue'!M17 | R18: 1325.6811 | S18: =Q18-R18 | T18: ='6. Rates & revenue'!Q17 | U18: 1085.3726 | V18: =T18-U18 | W18: ='6. Rates & revenue'!U17 | X18: 187.96044 | Y18: =W18-X18 | Z18: ='6. Rates & revenue'!Y17 | AA18: 2111.8128 | AB18: =Z18-AA18 | AC18: ='7. NLTF rollup'!G17 | AD18: 2454.0284 | AE18: =AC18-AD18 | AF18: ='7. NLTF rollup'!P17 | AG18: 4786.9982 | AH18: =AF18-AG18 | AI18: ='7. NLTF rollup'!W17 | AJ18: 7713.1668 | AK18: =AI18-AJ18
... A31: 2050 | B31: ='6. Rates & revenue'!H30 | C31: 593.20136 | D31: =B31-C31 | E31: ='6. Rates & revenue'!I30 | F31: 1032.0361 | G31: =E31-F31 | H31: ='5. Light fleet split'!S30 | I31: 5760.3024 | J31: =H31-I31 | K31: ='5. Light fleet split'!P30 | L31: 37517.253 | M31: =K31-L31 | N31: ='5. Light fleet split'!Q30 | O31: 2651.9312 | P31: =N31-O31 | Q31: ='6. Rates & revenue'!M30 | R31: 959.14796 | S31: =Q31-R31 | T31: ='6. Rates & revenue'!Q30 | U31: 6246.9978 | V31: =T31-U31 | W31: ='6. Rates & revenue'!U30 | X31: 217.75007 | Y31: =W31-X31 | Z31: ='6. Rates & revenue'!Y30 | AA31: 3249.8557 | AB31: =Z31-AA31 | AC31: ='7. NLTF rollup'!G30 | AD31: 1029.5881 | AE31: =AC31-AD31 | AF31: ='7. NLTF rollup'!P30 | AG31: 11349.702 | AH31: =AF31-AG31 | AI31: ='7. NLTF rollup'!W30 | AJ31: 12827.536 | AK31: =AI31-AJ31
A32: Largest difference | D32: =MAX(MAX(D7:D31),-MIN(D7:D31)) | G32: =MAX(MAX(G7:G31),-MIN(G7:G31)) | J32: =MAX(MAX(J7:J31),-MIN(J7:J31)) | M32: =MAX(MAX(M7:M31),-MIN(M7:M31)) | P32: =MAX(MAX(P7:P31),-MIN(P7:P31)) | S32: =MAX(MAX(S7:S31),-MIN(S7:S31)) | V32: =MAX(MAX(V7:V31),-MIN(V7:V31)) | Y32: =MAX(MAX(Y7:Y31),-MIN(Y7:Y31)) | AB32: =MAX(MAX(AB7:AB31),-MIN(AB7:AB31)) | AE32: =MAX(MAX(AE7:AE31),-MIN(AE7:AE31)) | AH32: =MAX(MAX(AH7:AH31),-MIN(AH7:AH31)) | AK32: =MAX(MAX(AK7:AK31),-MIN(AK7:AK31))
A34: =IF(MAX(B32:AK32)<0.01,"MATCH: every line reconciles to the dashboard within $0.01m / 0.01m km","CHECK: a line differs - inspect the difference columns")

Sheet 9. Mapping & glossary
A1: Where every line comes from - and what the jargon means
A4: Series mapping: this workbook <-> the dashboard <-> MoT
A5: Plain-language line (this workbook) | B5: Dashboard series | C5: MoT / MBU26 source | D5: MoT VFM role | E5: Notes
A6: Petrol travel per person | B6: PED VKT per capita | C6: MBU26 sheet row 17 (history/official) | D6: Petrol share of light VKT (sheet 2, col F) | E6: Forecast by the AR(1) time-series model each quarter; the only line that differs between the two engines.
A7: Petrol pool (million km) | B7: light_petrol_vkt | C7: MBU26 sheet row 16 | D7: Petrol VKT by scenario | E7: Travel per person x population, summed over the four quarters of the June year.
A8: Light RUC pool (million km) | B8: light_ruc_net_km (model total) | C8: MBU26 sheet row 10 | D8: Light pool = diesel + diesel-hybrid + BEV + PHEV | E8: The light RUC model forecasts the whole light RUC universe; the class split happens on sheet 5.
A9: Conventional light RUC km | B9: light_ruc_net_km (committed) | C9: MBU26 row 10 (share), row 33 (revenue) | D9: Diesel + diesel-hybrid VKT | E9: Light pool minus the electric switch drawn from it.
A10: Battery-electric light km | B10: light_bev_ruc_net_km | C10: MBU26 row 12 (share), row 35 (revenue) | D10: 'Electric' VKT for LPV+LCV | E10: Light universe x MoT BEV share.
A11: Plug-in hybrid km | B11: phev_ruc_net_km | C11: MBU26 row 14 (share), row 37 (revenue) | D11: 'Petrol plug-in' VKT | E11: Light universe x MoT PHEV share.
A12: Heavy RUC km | B12: heavy_ruc_net_km | C12: MBU26 row 11 (km), row 34 (revenue) | D12: M Truck + H Truck VKT; electric share tracked separately | E12: Forecast directly by the heavy model; heavy BEVs pay the same per-km rate, so electrification is revenue-neutral inside the heavy block.
A13: Petrol litres and duty | B13: ped_volume / gross_ped_revenue | C13: MBU26 rows 15 (litres) and 45 (revenue) | D13: - | E13: Litres = petrol km x MoT fuel intensity; revenue = litres x MoT effective duty rate (legislated FY2027 +6c and FY2028 +12c steps included).
A14: Registration, LPG/CNG, refunds, admin, TUC | B14: net_mvr_revenue etc. | C14: MBU26 rows 36-63 | D14: - | E14: Taken from MBU26 as-is - not modelled.
A15: Total NLTF revenue | B15: total_nltf_net_revenue | C15: MBU26 rows 66-70 (official rollup) | D15: - | E15: Net fuel excise + net RUC + net registration + track user charge.
A17: Glossary
A18: NLTF | B18: National Land Transport Fund - where fuel excise, road user charges, registration and track user charges land.
A19: PED | B19: Petrol excise duty. 'PED volume' is petrol litres sold; 'PED VKT per capita' is petrol-vehicle kilometres travelled per person.
A20: RUC | B20: Road user charges - distance-based charges for vehicles that do not pay fuel excise (diesel, electric, heavy).
A21: VKT | B21: Vehicle kilometres travelled.
A22: BEV / PHEV | B22: Battery-electric vehicle / plug-in hybrid electric vehicle.
A23: MBU26 | B23: MoT's official 2026 baseline update - the published revenue model this dashboard benchmarks against.
A24: VFM 202405 | B24: MoT's Vehicle Fleet Model (May 2024 run) - projects the fleet's power-type mix; source of the EV transition curves.
A25: MVR / MR1 / MR2 / COO | B25: Motor vehicle registration revenue components and the certificate-of-ownership fee.
A26: TUC | B26: Track user charges (rail).
A27: June year | B27: The transport funding year: FY2030 runs July 2029 to June 2030.
A28: ex GST | B28: All dollars exclude GST, matching MoT's published basis.
A29: AR(1) model | B29: Our production PED model: a regression with statistically well-behaved (autocorrelation-corrected) errors; passes all six core diagnostic tests.
